[
  {
    "bookSourceComment": "//使用需要改包名(现在不用了),魔法\n//❗如果你打算去除所有书源信息并公开的话，那不好意思，服务器随时关停，搜索缺书现象请反馈\n//By情无羁(yesui.me)25.01.25修改部分规则,个人用法：点登录后选择强制保持站点然后打钩，搜索后过cf盾显示列表为0后重新搜索即可\n25.02.16修改部分规则，修改发现规则\n25.02.20修复封面\n25.03.04完善规则\n25.03.13绕过me域名验证\n25.03.26完善发现(感谢Buding)\n25.03.30修复封面\n25.04.08修复封面\n25.05.08搜索免cf盾(有缺老书现象,可以先添加网址,然后反馈给制作者)\n靈狐 制，可拷贝书源，更改源URL当不同源用\n书架书籍与源URL绑定，如站点变动可在登录里自定义站点来避免重新添加书架\n24-05-13 修复乱序\n24-06-04 发现与更多模板支持\n理论支持全部69网站使用，发现若错乱请刷新\n24-07-02 支持更多模板，部分站点只有排行榜，暂不予适配发现\n24-07-13 目录排序，支持无标记正文排序，支持设置源变量改变搜索、发现\n24-07-18 发现支持筛选、单页，源变量设置可改变所有页面，优化正文标题净化\n24-09-18 支持移除目录重复条目，详情页添加标签，移除正文解密、排序，登录进行源站相关设置（强制保持：强制替换站点为当前站点），添加过cf盾\n24-09-20 避免因Cookie丢失导致页面被缓存无法过盾，可设置封面为69默认封面\n24-09-21 添加新的封面链接，加入随机UA功能\n24-09-28 修复站点目录，发现添加最近更新（如果有），封面修复改良\nhttps://www.69shu.cx\nhttps://www.69shuba.pro\nhttps://www.69yuedu.net\nhttps://69shuba.cx\nhttps://69shu.ac",
    "bookSourceGroup": "",
    "bookSourceName": "原69主站",
    "bookSourceType": 0,
    "bookSourceUrl": ".com域名",
    "bookUrlPattern": "https?:\\/\\/.*69(yuedu|shuba)\\.(cx|com|me|net)\\/(book|article)\\/.*",
    "concurrentRate": "",
    "coverDecodeJs": "",
    "customOrder": 1,
    "enabled": true,
    "enabledCookieJar": false,
    "enabledExplore": true,
    "exploreUrl": "@js:\n\nvar sort=[],\npush=(title,surl,size)=>sort.push({\n    title: title,\n    url: surl,\n    style: {\n      layout_flexGrow: 1,\n      layout_flexBasisPercent: size,\n     }\n  });\n\t\npush(\"༺ˇ»`ʚ最近更新ɞ´«ˇ༻\",\"{{getUrl}}/last.html\",1,1);\n\n\n[[\"男生\",\"male\"],[\"女生\",\"female\"]].map([title,uri]=>push(title, `{{getUrl}}/novels/${uri}`,  0.4));\n\npush(\"༺ˇ»`ʚ人气ɞ´«ˇ༻\",\"{{getUrl}}/novels/monthvisit_0_0_{{page}}.htm\",1);\n\n\n[[\"连载\",\"monthvisit_0_2_\"],[\"全本\",\"monthvisit_0_1_\"],[\"推荐\",\"allvote_0_0_\"],[\"新书\",\"newhot_0_0_\"]].map([title,uri]=>push(title, `{{getUrl}}/novels/${uri}{{page}}.htm`, 0.2));\n\n\nvar xiaoyu=[\"༺ˇ»`ʚ全部新书ɞ´«ˇ༻\",\"玄幻魔法\",\n\"修真武侠\",\"言情小说\",\"历史军事\",\n\"游戏竞技\",\"科幻空间\",\"悬疑惊悚\",\n\"同人小说\",\"都市小说\",\"官场职场\",\n\"穿越时空\",\"青春校园\"];\nxiaoyu.map((title,i)=>{\n\tlink=`{{getUrl}}/novels/newhot_${i}_0_{{page}}.htm`;\n\tif(i==0){\n\t\tsize=1\n\t\t}else{size=0.25}\n\tpush(title,link,size)\n\t});\n\n\nvar tuomasi=[\"༺ˇ»`ʚ全部人气ɞ´«ˇ༻\",\"玄幻魔法\",\n\"修真武侠\",\"言情小说\",\"历史军事\",\n\"游戏竞技\",\"科幻空间\",\"悬疑惊悚\",\n\"同人小说\",\"都市小说\",\"官场职场\",\n\"穿越时空\",\"青春校园\"];\ntuomasi.map((title,i)=>{\n\tlink=`{{getUrl}}/novels/monthvisit_${i}_0_{{page}}.htm`;\n\tif(i==0){\n\t\tsize=1\n\t\t}else{size=0.25}\n\tpush(title,link,size)\n\t});\n\n\nvar linghu=[\"༺ˇ»`ʚ全部连载ɞ´«ˇ༻\",\"玄幻魔法\",\n\"修真武侠\",\"言情小说\",\"历史军事\",\n\"游戏竞技\",\"科幻空间\",\"悬疑惊悚\",\n\"同人小说\",\"都市小说\",\"官场职场\",\n\"穿越时空\",\"青春校园\"];\nlinghu.map((title,i)=>{\n\tlink=`{{getUrl}}/novels/monthvisit_${i}_2_{{page}}.htm`;\n\tif(i==0){\n\t\tsize=1\n\t\t}else{size=0.25}\n\tpush(title,link,size)\n\t});\n\n\nvar youke=[\"༺ˇ»`ʚ全部全本ɞ´«ˇ༻\",\"玄幻魔法\",\n\"修真武侠\",\"言情小说\",\"历史军事\",\n\"游戏竞技\",\"科幻空间\",\"悬疑惊悚\",\n\"同人小说\",\"都市小说\",\"官场职场\",\n\"穿越时空\",\"青春校园\"];\nyouke.map((title,i)=>{\n\tlink=`{{getUrl}}/novels/monthvisit_${i}_1_{{page}}.htm`;\n\tif(i==0){\n\t\tsize=1\n\t\t}else{size=0.25}\n\tpush(title,link,size)\n\t});\n\nvar nanfeng=[\"༺ˇ»`ʚ全部推荐ɞ´«ˇ༻\",\"玄幻魔法\",\n\"修真武侠\",\"言情小说\",\"历史军事\",\n\"游戏竞技\",\"科幻空间\",\"悬疑惊悚\",\n\"同人小说\",\"都市小说\",\"官场职场\",\n\"穿越时空\",\"青春校园\"];\nnanfeng.map((title,i)=>{\n\tlink=`{{getUrl}}/novels/allvote_${i}_0_{{page}}.htm`;\n\tif(i==0){\n\t\tsize=1\n\t\t}else{size=0.25}\n\tpush(title,link,size)\n\t});\n\n\n\n\n\npush(\"༺ˇ»`ʚ标签ɞ´«ˇ༻\",null,1,1);\ntag=[\"穿越\",\"轻松\",\"系统流\",\"同人衍生\",\"重生\",\"女强\",\"甜宠\",\"1V1\",\"爽文\",\"无敌流\",\"热血\",\"豪门\",\"腹黑\",\"扮猪吃虎\",\"种田\",\"宅斗\",\"日久生情\",\"HE\",\"逆袭\",\"经营\",\"杀伐果断\",\"快节奏\",\"日常文\",\"架空\",\"欢喜冤家\",\"权谋\",\"总裁\",\"打脸\",\"强强\",\"家长里短\",\"萌宝\",\"校园\",\"无限流\",\"智商在线\",\"冷静\",\"空间\",\"宫斗\",\"异能\",\"诸天流\",\"快穿\",\"先婚后爱\",\"脑洞大\",\"帝王\",\"金手指\",\"穿书\",\"大佬\",\"文娱\",\"娱乐圈\",\"赚钱\",\"强者归来\",\"婚恋\",\"明星\",\"青梅竹马\",\"痴情\",\"草根崛起\",\"斗罗大陆\",\"年代文\",\"相爱相杀\",\"兵王\",\"温馨\",\"升级流\",\"爆笑\",\"天才流\",\"美食\",\"洪荒\",\"搞笑\",\"王爷\",\"争霸\",\"游戏异界\",\"星际\",\"霸道\",\"破镜重圆\",\"综漫\",\"谋略\",\"致富\",\"一见钟情\",\"双洁\",\"开局流\",\"时空文\",\"正能量\",\"团宠\",\"护短\",\"学生\",\"马甲\",\"成熟\",\"修真\",\"多女主\",\"智斗\",\"养成\",\"虐渣\",\"单女主\",\"女配\",\"玄学\",\"复仇\",\"双向暗恋\",\"修仙\",\"医生流\",\"励志\",\"王妃\",\"三观正\",\"签到\",\"进化\",\"召唤流\",\"女扮男装\",\"灵气复苏\",\"思路清奇\",\"嫡女\",\"神话\",\"电竞\",\"搞怪\",\"皇后\",\"无节操\",\"护花高手\",\"独宠\",\"古典仙侠\",\"三国\",\"升级\",\"男神\",\"悬疑流\",\"同居\",\"异兽流\",\"乱世\",\"傲娇\",\"隐婚\",\"西游\",\"战争\",\"布局流\",\"神医\",\"废柴流\",\"现代修真\",\"高冷\",\"反套路\",\"武道\",\"萌系\",\"别后重逢\",\"架空历史\",\"明朝\",\"谨慎\",\"偏执\",\"虐文\",\"时空门\",\"探险\",\"唐朝\",\"学霸\",\"未来世界\",\"科举\",\"自律\",\"奋斗\",\"科技\",\"学院流\",\"爱情\",\"吐槽\",\"封神\",\"可盐可甜\",\"校草\",\"直播文\",\"无金手指\",\"朝堂\",\"练功\",\"日系\",\"魔法\",\"军旅\",\"LOL\",\"网游\",\"治愈\",\"强国\",\"异世穿越\",\"御兽流\",\"农门\",\"炼丹\",\"世家\",\"契约婚姻\",\"恋爱\",\"群像\",\"都市修仙\",\"全能\",\"古灵精怪\",\"黑化\",\"朝堂江湖\",\"闪婚\",\"无CP\",\"巧娶\",\"正剧\",\"宠物\",\"克苏鲁\",\"特种兵\",\"凡人流\",\"侦探推理\",\"前世今生\",\"幕后流\",\"强者流\",\"位面\",\"影后\",\"职场商战\",\"随身流\",\"秦汉\",\"超A\",\"悬疑推理\",\"技术流\",\"思想迪化\",\"首席\"];\ntag.map((title,index)=>{\t\t\n\n\tif(index+1 <= tag.length - tag.length%3){\n\t\t\tpush(title, `{{getUrl}}/tag/${title}/{{page}}/`, 0.25);}\n\t\t\telse{ push(title, `{{getUrl}}/novels/tag/${title}/{{page}}/`,0.25);}\n\t\t\t});\n\nJSON.stringify(sort);",
    "header": "@js:\nif(!java.getWebViewUA&&!v('ua'))v('ua', randomUa())\nheaders = {\n\t\"Accept-Language\": \"zh-CN,zh;q=0.9,en-US;q=0.8,en;q=0.7\",\n\t\"Referer\":\"https://69shuba.cx/blist/\",\n\t\"cookie\":\"zh_choose=s\",\n\t\"User-Agent\": v('ua') || java.getWebViewUA()\n}\nif(v('lock')||v('img')){\n\theaders[\"X-Requested-With\"] = \"io.bro\"\n\theaders[\"Cache-Control\"] = \"no-cache\"\n}\nJSON.stringify(headers)",
    "jsLib": "function v(key, value, del){\n\tconst {source} = this\n\tlet data = source.variable\n\ttry{data = JSON.parse(data)}catch(e){data = {}}\n\tif(!!value||value==0)data[key] = value\n\tif(del)delete data[key]\n\tsource.variable = JSON.stringify(data)\n\treturn data[key]\n}\nfunction cf(url, times){\n\tconst {cache, java, cookie} = this\n\tlet f = (n,v,d) => this.v(n,v,d), result, id = (Math.random()+0.1)*10, times = times?times:0, yz = url\n\tif(/search.php,/.test(yz))yz = completeUrl.call(this, '/',yz)\n\ttry{\n\t\tif(!f('ok')&&!f('lock')){\n\t\t f('lock', id)\n\t\t java.log(id)\n\t\t if(f('lock') == id){\n\t\t \tresult = java.startBrowserAwait(yz,\"验证\"), e()\n\t\t }\n\t }\n\t}catch{f('ok', 1);f('lock', null, 1)}\n\twhile(f('lock')){}\n\tif(yz!=url||!result||result.body().match('_cf_')){\n\t\tresult = java.connect(url)\n\t\tif(result.body().match('_cf_')){\n\t\t\tf('ok', null, 1)\n\t\t\tif(times==0)result = cf.call(this, url, times+1)\n\t\t}\n\t}\n\treturn result\n}\nfunction fixImg(img, url){\n\tconst {java} = this\n\tif(!v.call(this, 'f')&&!/\\ds\\.jpg$/.test(img)){\n\t\tlet m=url.match(/\\/(\\d+)(\\.[^.]*)?$/)\n\t\tif(!m)return img\n\t\timg = this.completeUrl('/bimages/'+Math.floor(m[1]/1000)+'/'+m[1]+'/'+m[1]+'s.jpg', url)\n\t}\n\treturn img\n}\nfunction randomUa(){\n\tlet r = (a,b) => Math.floor(Math.random()*(b-a)+a), x = l =>{for(i=0,s='';i<l;i++){s+=r(0,10)}return s}, v = r(500, 700)+'.'+x(2)\n\treturn `Mozilla/5.0 (Linux; Android ${r(5,15)}; wv) AppleWebKit/${v} (KHTML, like Gecko) Chrome/${r(76,122)}.0.${x(4)}.${x(2)} Mobile Safari/${v}`\n}\nfunction getDomain(){\n\tconst {source} = this\n\tlet domain = v.call(this, 'Domain')\n\tif(!domain||domain=='')domain=source.key\n\treturn domain\n}\nfunction completeUrl(url, base) {\n  let baseUrl = base || getDomain.call(this)\n  if(v.call(this,'k'))url = String(url).replace(/.*\\/\\/[^/]+/, '')\n  let m = baseUrl.match(/(.+?)\\/\\/([^/]+)(.*\\/?)(.*)/)\n  let fill = ''\n  if (url.match(/^https?:/)) {\n  } else if (url.match(/^\\/\\//)) {\n    fill = m[1]\n  } else {\n    fill = m[1] + '//' + m[2]\n    if (!url.match(/^\\//)){\n    \tfill = fill + m[3]\n    }\n  }\n  return fill + url\n}\nvar getUrl='https://www.69shuba.com/'",
    "lastUpdateTime": "1746789857938",
    "loginCheckJs": "src=result.body()\nurl=result.url()\nif(src.match('为了获得最佳体验，请使用新版本的Google Chrome 或者其他主流浏览器访问此网站')){\n\ttry{\n\t\tif(!cache.get('cwmlock')){\n\t\t cache.put('cwmlock',1,60)\n\t\t result=java.startBrowserAwait(url,\"验证\")\n\t  cache.delete('cwmlock')\n\t }\n\t}catch{\n\t\tcache.delete('cwmlock')\n\t}\n\twhile(cache.get('cwmlock')){}\n\tif(result.body().match('_cf_')){\n\t\tresult=java.connect(url)\n\t}\n}\nresult",
    "loginUi": "[\n{\n\t\"name\": \"免费书源请输入源作者\",\n\t\"type\": \"text\"\n\t},\n    {\n        name: \"\\t\\t获取随机UA\\t\\t\\t\",\n        type: \"button\",\n        action: \"t=`\\n如果出现问题请重启阅读`;if(v('ua'))v('ua',0,1),java.longToast('📱已恢复默认UA'+t);else ua=randomUa(),v('ua',ua),java.longToast(`🔀已获得随机UA${t}\\n${ua}`)\"\n    }\n]",
    "loginUrl": "function login(){\n\tv('Domain',source.getLoginInfoMap().自定义站点)\n}",
    "respondTime": 180000,
    "ruleBookInfo": {
      "author": "<js>\nif (src.match(/69shuba/)){\n\tjava.getString('p.0@text')\n\t}else {\n\t\tjava.getString('.bauthor@text')\n\t\t}\n</js>##作者：|\\/.*",
      "canReName": "",
      "coverUrl": "<js>java.getString('img@data-src||img@src')\n</js>##.*\\/(\\d+)(\\d{3}).*##https://static.69shuba.com/files/article/image/$1/$1$2/$1$2s.jpg###||.bimgbox@img@src",
      "init": "<js>\nif (src.match(/404 Not Found/)){\n\tb=baseUrl.match(/\\/book.*/)\n\tre='https://www.69yuedu.co'+b\n\tr=java.ajax(re);\n\t}else {\n\t\tr=result\n\t\t}r\n</js>",
      "intro": "<js>\nif (src.match(/69shuba/)){\n\tjava.getString('.navtxt@p!-1@html')\n\t}else {\n\t\tjava.getString('.bjianjie@html')\n\t\t}\n</js>",
      "kind": "p[1:3]@text##.+：\n<js>##\\s\\|\\s##,</js>",
      "lastChapter": ".qustime@ul@li.0@text||.zjbox@ul@li.0@text",
      "name": "h1@text",
      "tocUrl": "<js>\nif (src.match(/69shuba/)){\n\turl=baseUrl.replace(/\\.html?/,'/')\n\t}else {\tbaseUrl.replace(/.*(\\/book)/,'https://www.69yuedu.co$1')\n\t\t}\n</js>",
      "wordCount": ""
    },
    "ruleContent": {
      "content": "<js>\nif(result.match(/Just a moment/)){\n\tjava.startBrowserAwait(baseUrl,\"验证\");\n\tresult=java.ajax(baseUrl);\n}result;\n</js>\n.txtnav@html||.content@html||.contxt@html##<h1[\\s\\S]+?</h1>|^\\s*<[a-z]+ .*>|<\\/[a-z]+>$|(?<!^)<div[\\s\\S]*?</div>\\s*",
      "replaceRegex": "##\\s*\\(本章完\\)\\s*$|第.*章.*",
      "title": "h1@text##《{{book.name}}》|正文卷.|正文.|VIP卷.|默认卷.|卷_|VIP章节.|免费章节.|章节目录.|最新章节.|[\\(（【].*?[求含理更谢乐发推票盟补加字].*?[】）\\)]\n@js:result\n.replace(\"••\",\"\")\n.replace(/^(\\d+).第/,'第')\n.replace(/^(\\d+)[、．]第.+章/,'第$1章')\n.replace(/^(\\d+)、\\d+、/,'第$1章 ')\n.replace(/^(\\d+)、\\d+/,'第$1章')\n.replace(/^(第.+章)\\s?\\d+/,'$1')\n.replace(/^(\\d+)、/,'第$1章 ')\n.replace(/^(第.+章)\\s?第.+章/,'$1')\n.replace(/第\\s(.+)\\s章/,'第$1章')\n.replace(/.*(chapter|Chapter)\\s?(\\d+)\\s?/,'$1 $2 ')\n.replace(/\\(.+\\)/,'')\n.replace(/\\[|。/,'')\n.replace(/第([零一二两三四五六七八九十百千]+)章/g,java.toNumChapter(result))\n##(章)([^\\s]+)(\\s·)##$1 $2$3"
    },
    "ruleExplore": {
      "author": "class.labelbox@label.0@text",
      "bookList": "ul@class.newnav||.recentupdate2@ul@li",
      "bookUrl": "a.0@href",
      "coverUrl": "a.0@href##.*\\/(\\d+)(\\d{3}).*##https://static.69shuba.com/files/article/image/$1/$1$2/$1$2s.jpg###",
      "intro": "class.ellipsis_2@text",
      "kind": "class.labelbox@label.2@text&&class.labelbox@label.1@text",
      "lastChapter": "@p.-1@html||a.1@text##.*最近章节.*",
      "name": "h3@text||a.0@text",
      "wordCount": ""
    },
    "ruleSearch": {
      "author": "$.author",
      "bookList": "<js>\n(()=>{var ޢˈ='ᠦʹ'&'ˌᐠ',ᣟⵯ=-~'ᠤꧦ',ܙו=ᣟⵯ-~'ㆍⲲ',ˌꞋ=ܙו+ܙו,ㆴމ=ˌꞋ*ܙו,ʺᐝ=ܙו*ˌꞋ*ܙו,ˆߴ=ㆴމ*ˌꞋ,ᣚາ=ˌꞋ*ʺᐝ,ᱹܕ=ㆴމ*ܙו*ㆴމ,ᣞﾞ=ᣚາ*ˌꞋ,ᵔޚ=ㆴމ*ᣚາ,ᠩᐨ=ˌꞋ*ᣞﾞ,ﾞꓽ=ᣚາ*ˆߴ,ᒻܢ=ᣞﾞ*ʺᐝ,ܯހ=ㆴމ*ᠩᐨ,ᠹเ=ˆߴ*ᵔޚ,ܝܖ=ˌꞋ*ܯހ,ᓐཐ=!ᣟⵯ+[],ㆶء=ᓐཐ[ޢˈ],ۀꓻ=ㆶء[ᣟⵯ]+[],ᛍᒾ=ᓐཐ[ᣟⵯ],ᠦเ=ᓐཐ[ܙו],ᱸⰍ=ᓐཐ[ܙו+ᣟⵯ],ᓪゝ=ᓐཐ[ˌꞋ],ꜚヽ=ۀꓻ[ˌꞋ+ᣟⵯ],ᚐꞈ=[]+{},ᔅᐧ=ᚐꞈ[ˌꞋ+ᣟⵯ],ۀᱹ=ᚐꞈ[ܙו],ཋᐧ=ۀꓻ[ޢˈ],ᱹᒻ=ۀꓻ[ᣟⵯ],ᖮﾟ=(!ޢˈ+[])[ޢˈ],ᒢｰ=ᚐꞈ[ᣟⵯ],ͺـ=ᚐꞈ[ㆴމ-ᣟⵯ],ۀາ=ۀꓻ[ܙו],ᱺە=(!ޢˈ+[])[ᣟⵯ],ᣚމ=ᔅᐧ+ᒢｰ+ᱹᒻ+ᱸⰍ+ᖮﾟ+ᱺە+ཋᐧ+ᔅᐧ+ᖮﾟ+ᒢｰ+ᱺە,ᣙⲲ=[][ㆶء+ꜚヽ+ᠦเ+ᖮﾟ+ᓪゝ+ᱺە],བꓹ=ᣙⲲ[ᣚމ],ۂⲲ=''[ᣚމ]+[],ᱸˊ=ۂⲲ[ᣟⵯ+ㆴމ],ᣟᆢ=ۂⲲ[ʺᐝ-ܙו],ꜚᱻ=ᖮﾟ+ᒢｰ+ᱸˊ+ᖮﾟ+ᱺە+ꜚヽ+ᱹᒻ+ᣟᆢ,ᠰˑ=(ᣟⵯ+ㆴމ+ʺᐝ)[ꜚᱻ](ˆߴ),ꞈๅ=[][ᣚމ][ᣚމ](ᱺە+ᓪゝ+ᖮﾟ+ཋᐧ+ᱺە+ᱹᒻ+ͺـ+ᓪゝ+ᱸⰍ+ᔅᐧ+ᛍᒾ+ᠰˑ+ᓪゝ)(),ᒡۃ=ꞈๅ(''[ۀᱹ+ꜚヽ+ᣟᆢ]())[ܙו],ᐦᅳ=(ʺᐝ+ˌꞋ+ܙו)[ꜚᱻ](ˆߴ),ᒽー=(ʺᐝ+ᣟⵯ)[ꜚᱻ](ˆߴ),ᕝހ=(ˆߴ-ᣟⵯ)[ꜚᱻ](ˆߴ),ᠥས=''[ᣚމ][ㆶء+ᱺە+ᒢｰ+ᐦᅳ+ᒡۃ+ᒽー+ᛍᒾ+ᱺە+ᒡۃ+ᒢｰ+ۀາ+ᓪゝ],ʽⰍ=བꓹ(ᱺە+ᓪゝ+ᖮﾟ+ཋᐧ+ᱺە+ᱹᒻ+ͺـ+ᓪゝ+ᕝހ+ᛍᒾ+ᠦเ)(),ⵗஃ=ˆߴ+ᣚາ|ㆴމ|ܙו+ˌꞋ,ᕐᱺ=ㆴމ+ᣞﾞ|ᵔޚ+ˌꞋ+ˆߴ+ܯހ+ᠩᐨ|ᠹเ,ᒡꓹ=ܝܖ+ܙו|ʺᐝ+ᠩᐨ+ᣞﾞ|ㆴމ+ﾞꓽ+ᵔޚ|ܯހ|ᠹเ+ᒻܢ,ꓼߵ=ᣚາ|ʺᐝ|ᣟⵯ|ˆߴ,ᠧⵯ=ܯހ+ᠹเ+ㆴމ|ᒻܢ+ᣞﾞ|ˆߴ+ᠩᐨ,ᛍܝ=ᣚາ+ᵔޚ|ᠩᐨ+ᠹเ+ㆴމ+ʺᐝ|ﾞꓽ|ᱹܕ,ᐥヽ=ˌꞋ+ᣟⵯ+ʺᐝ+ᣚາ+ㆴމ,ߑʻ=ᣚາ|ᣟⵯ+ʺᐝ|ˌꞋ|ˆߴ,ˌˑ=ʺᐝ+ᣟⵯ+ㆴމ|ˆߴ,ᠱꓻ=ˆߴ,ﾟܚ=ㆴމ+ˌꞋ+ˆߴ,ᱹᒽ=ᣚາ+ᣞﾞ|ᱹܕ|ᠹเ+ᒻܢ|ᣟⵯ|ʺᐝ|ᵔޚ,ܪݥ=ᣟⵯ|ㆴމ+ʺᐝ+ᣚາ,ʻゝ=ᣚາ+ˌꞋ|ʺᐝ+ㆴމ,ۃட=ˆߴ|ᠩᐨ+ᠹเ+ᱹܕ+ᵔޚ|ﾞꓽ|ˌꞋ,ˆᐝ=ﾞꓽ+ᵔޚ|ᠹเ+ܯހ|ʺᐝ+ᠩᐨ|ᱹܕ,ٴߑ=ﾞꓽ+ᵔޚ+ᠩᐨ|ʺᐝ+ˆߴ+ㆴމ+ܙו+ᠹเ,ᱺᅳ=ᣟⵯ|ᣚາ+ᵔޚ|ᣞﾞ|ᱹܕ+ﾞꓽ+ܝܖ,ꓸە=ˆߴ|ᣟⵯ|ܙו+ˌꞋ|ㆴމ,ᠸว=ᣚາ+ʺᐝ,ᠴހ=ᵔޚ+ܯހ+ᣚາ+ᠹเ+ᣞﾞ+ᱹܕ+ʺᐝ,ʽະ=ᠩᐨ|ᒻܢ|ﾞꓽ|ᠹเ|ܙו|ʺᐝ|ᣟⵯ+ᵔޚ|ᣞﾞ|ᣚາ,ᠦⲺ=ᣚາ|ˆߴ|ᣟⵯ|ܙו,ހᐨ=ᣚາ|ᣟⵯ+ܙו,ⴰʹ=ﾞꓽ+ᠹเ+ᱹܕ+ᠩᐨ+ˆߴ+ܯހ|ᒻܢ+ˌꞋ+ᵔޚ|ᣞﾞ,ˈꓻ=ᣚາ|ㆴމ|ܙו,ܪゝ=ᣚາ|ܙו|ᣟⵯ|ˆߴ+ㆴމ,ͺˑ=ˌꞋ|ܙו+ᠩᐨ+ᵔޚ+ᣚາ|ᣟⵯ+ᣞﾞ|ܯހ|ʺᐝ,ㆍำ=ʺᐝ+ᣞﾞ|ᒻܢ|ㆴމ+ˆߴ+ᠹเ+ܙו+ᵔޚ,ᠤߑ=ᣚາ+ㆴމ|ˆߴ|ܙו,ᕐܕ=ˆߴ|ㆴމ|ᣟⵯ|ܙו|ᣚາ|ˌꞋ,ᕝˑ=ᣚາ+ᣟⵯ+ˌꞋ+ʺᐝ,ʹ〳=ᣚາ+ᣟⵯ|ܙו+ˌꞋ+ʺᐝ+ㆴމ,ᠲང=ᣚາ|ˌꞋ|ᣟⵯ,ꓹᑉ=ᠹเ|ᣞﾞ|ܙו|ㆴމ|ﾞꓽ+ܯހ+ˌꞋ+ʺᐝ+ᒻܢ|ˆߴ,ㆴꧦ=ᠩᐨ+ܙו+ᠹเ+ﾞꓽ|ᣚາ|ˌꞋ+ˆߴ|ᵔޚ,ءˋ=ˌꞋ|ˆߴ+ᣟⵯ|ㆴމ+ᣚາ,ᠦՙ=ˌꞋ|ᣟⵯ|ܙו|ᣚາ,ꓸᓐ=ﾞꓽ|ᣚາ|ᵔޚ|ˆߴ|ʺᐝ|ᠩᐨ|ᠹเ,ۃՙ=ʺᐝ+ˆߴ+ܙו,ꓽꜤ=ᠹเ|ᠩᐨ+ᵔޚ+ㆴމ+ܯހ+ᣟⵯ|ˌꞋ+ܙו|ˆߴ,ᢦߴ=ܙו+ˌꞋ+ʺᐝ+ᣟⵯ+ᣚາ,ˇܘ=ᣟⵯ+ˆߴ,ᣞས=ʺᐝ|ㆴމ+ˌꞋ|ᱹܕ+ᠹเ+ᣞﾞ|ᠩᐨ+ᵔޚ|ܯހ,ᠹˇ=ܙו+ﾞꓽ|ᣞﾞ+ᱹܕ|ᒻܢ+ᠹเ,ངו=ᠩᐨ|ᣚາ|ᣞﾞ|ᣟⵯ|ᠹเ|ܯހ+ﾞꓽ,ޚᎰ=ˆߴ+ᣚາ|ㆴމ+ʺᐝ,ޚݥ=ˌꞋ|ᣚາ,ᵕߪ=ᣚາ|ܙו|ˆߴ|ʺᐝ+ㆴމ,γہ=ʺᐝ|ˌꞋ|ˆߴ+ܙו,ˑー=ᣟⵯ+ʺᐝ+ˆߴ,ᶥೲ=ܯހ+ᣟⵯ+ᠹเ|ᣞﾞ+ﾞꓽ|ᵔޚ|ᣚາ|ˆߴ+ܙו,ᢥว=ᣚາ|ˆߴ|ㆴމ|ʺᐝ+ᣟⵯ,ᕝด=ܙו+ˆߴ|ˌꞋ+ᣚາ|ᣟⵯ,ꞈމ=ᣚາ|ܙו|ᣟⵯ|ʺᐝ,ہཐ=ʺᐝ+ᣟⵯ+ˆߴ|ˌꞋ+ㆴމ,ޢཐ=ʺᐝ|ᣚາ|ˆߴ,ߑߺ=ᣟⵯ|ܙו+ˌꞋ+ˆߴ|ʺᐝ,ᐞʹ=ㆴމ+ᣚາ|ˆߴ+ˌꞋ,ᐠͺ=ˆߴ|ˌꞋ+ᣚາ+ᣟⵯ,ᚲᄾ=ᠩᐨ|ᠹเ|ᣚາ|ᱹܕ+ܯހ|ˆߴ|ᣞﾞ,າߺ=ﾞꓽ|ㆴމ+ᵔޚ|ᠩᐨ+ܙו|ᠹเ,ᣞᱻ=ᣟⵯ|ˆߴ+ˌꞋ+ܙו,ܙ〵=ᣞﾞ+ᠹเ|ᣟⵯ|ㆴމ|ˌꞋ+ᒻܢ+ᣚາ,ᐠݚ=ᱹܕ+ᵔޚ|ᒻܢ|ᣚາ|ˌꞋ+ᣞﾞ+ㆴމ|ᠹเ+ᣟⵯ,ᔅヾ=ܙו|ㆴމ+ˆߴ|ᣟⵯ,ゝܕ=ܙו+ㆴމ+ˆߴ,ᐝꓻ=ᣞﾞ+ˆߴ|ᠹเ+ᣚາ+ᒻܢ+ㆴމ,ᐧܢ=ʺᐝ+ㆴމ|ᣚາ,ᠩᓐ=ܙו+ᣚາ+ʺᐝ,ᖕᒻ=ㆴމ+ˆߴ|ᣟⵯ,ޙเ=ᣟⵯ+ᣚາ|ˆߴ,ꜙเ=ﾞꓽ|ʺᐝ+ᒻܢ|ˆߴ+ᣟⵯ|ᠩᐨ+ᠹเ,བᵔ=ˆߴ+ᣟⵯ|ㆴމ+ᣚາ|ʺᐝ|ˌꞋ,ᠣས=ˆߴ|ᣚາ+ㆴމ,ⵂⲲ=ᣚາ|ˌꞋ+ʺᐝ|ᠩᐨ|ﾞꓽ+ᣞﾞ|ᠹเ|ㆴމ+ᵔޚ,ᣟꞈ=ˆߴ+ʺᐝ+ˌꞋ+ㆴމ|ᣚາ,ᖦʹ=ᣚາ+ˌꞋ|ˆߴ,ꧦᎱ=ᣚາ+ܙו|ˌꞋ+ʺᐝ,ᠧᱺ=ㆴމ+ˆߴ,ˇܖ=ㆴމ|ᣟⵯ+ܙו+ᣚາ,ܯⰍ=ᣚາ|ܯހ|ᱹܕ|ˌꞋ|ᣟⵯ+ᠹเ,ᣞʻ=ㆴމ+ᠹเ|ᵔޚ|ᒻܢ|ᣞﾞ|ﾞꓽ|ˌꞋ+ᱹܕ,ꓻˊ=ﾞꓽ|ᣟⵯ|ʺᐝ+ᣞﾞ|ˌꞋ|ㆴމ|ܙו|ˆߴ+ᵔޚ+ᠩᐨ+ᠹเ|ᣚາ,ᕐⲲ=ᒻܢ|ᣞﾞ|ܝܖ+ʺᐝ+ᱹܕ|ܙו|ﾞꓽ+ˌꞋ,ޚๅ=ᱹܕ|ᠩᐨ+ﾞꓽ+ㆴމ+ᣟⵯ+ˌꞋ|ᣚາ|ᣞﾞ+ʺᐝ|ᠹเ+ᵔޚ,ܯร=ˆߴ+ܙו|ㆴމ|ʺᐝ,ᔊາ=ˆߴ|ʺᐝ+ܙו|ᣚາ,ㆵہ=ܝܖ+ˌꞋ|ᣟⵯ,ᕐᄼ=ᠩᐨ|ᱹܕ+ᵔޚ|ˌꞋ|ᠹเ|ܙו+ﾞꓽ,ܖเ=ᒻܢ|ᣞﾞ|ﾞꓽ+ㆴމ+ᱹܕ+ܝܖ,ʺต=ᣚາ|ʺᐝ|ܙו+ˆߴ+ˌꞋ,ᖦߪ=ᒻܢ|ᠹเ+ᣞﾞ+ᣟⵯ+ᣚາ+ˆߴ+ˌꞋ,ʹᱹ=ˆߴ|ʺᐝ+ᣟⵯ+ㆴމ+ܙו,ᠦས=ܙו+ᣚາ+ˆߴ,ᚔܢ=ˌꞋ|ˆߴ|ㆴމ+ܙו,ᢜๅ=ˌꞋ|ㆴމ|ᣚາ,ᔈߴ=ʺᐝ|ᣚາ+ㆴމ+ܙו,ⵗᕀ=ᒻܢ+ᣞﾞ|ᠹเ+ᣟⵯ+ﾞꓽ|ᱹܕ|ᵔޚ|ᠩᐨ|ܯހ,ᵕꜢ=ʺᐝ+ᣟⵯ+ˆߴ+ˌꞋ,ۂˉ=ˆߴ|ˌꞋ|ܙו|ᣚາ,ᚔᄾ=ㆴމ+ˆߴ|ᣟⵯ+ᣚາ,ۀᐥ=ᣚາ|ܙו,ۃᔾ=ᠩᐨ|ㆴމ+ᣞﾞ+ᣟⵯ+ˌꞋ|ﾞꓽ|ܝܖ|ˆߴ,ᢥˉ=ˆߴ+ㆴމ+ˌꞋ|ᣟⵯ,ⵂߺ=ˌꞋ|ܙו|ㆴމ|ᣚາ,ᡟᒽ=ܙו|ᣞﾞ+ʺᐝ|ᒻܢ|ᱹܕ|ܝܖ,ءᔾ=ㆴމ+ʺᐝ|ܙו+ᣟⵯ+ᣚາ,ٴᱻ=ܙו+ˆߴ|ᣟⵯ+ܝܖ|ᒻܢ|ᱹܕ,ﾟꜢ=ᣟⵯ|ﾞꓽ+ᱹܕ|ˌꞋ|ܝܖ|ˆߴ+ʺᐝ+ᣚາ|ܙו|ᵔޚ+ᣞﾞ,ܯஃ=ʺᐝ|ˆߴ+ᣟⵯ+ㆴމ+ܙו|ˌꞋ,މˏ=ᣟⵯ|ʺᐝ|ܙו|ˆߴ,ᒼᓐ=ʺᐝ|ﾞꓽ|ᣞﾞ|ˆߴ|ᠩᐨ+ㆴމ|ᣟⵯ+ܝܖ,ᒽހ=ʺᐝ|ᣚາ|ˆߴ+ˌꞋ,މە=ʺᐝ+ܙו+ᣚາ+ᣟⵯ+ˆߴ,ʾʹ=ˆߴ+ʺᐝ+ᣚາ|ᣟⵯ|ㆴމ+ܙו,ྋͺ=ˆߴ|ʺᐝ,ہː=ʺᐝ|ˌꞋ|ᣚາ,ᠱⵯ=ᣚາ+ˌꞋ|ㆴމ|ᣟⵯ,ᠲꓺ=ˆߴ+ܙו+ᣚາ+ˌꞋ|ʺᐝ|ᣟⵯ,ͺܖ=ˆߴ+ˌꞋ|ʺᐝ,ᢜމ=ʺᐝ+ㆴމ+ˆߴ,ᠧܪ=ㆴމ|ᱹܕ+ܯހ+ˆߴ|ᠹเ,ᠹʺ=ᠩᐨ+ﾞꓽ|ʺᐝ|ᠹเ+ᒻܢ+ㆴމ|ᵔޚ|ˆߴ,ᠣˇ=ᣚາ+ᣟⵯ|ㆴމ,ᠷᑊ=ܙו+ʺᐝ|ᱹܕ|ܝܖ|ᠩᐨ|ᵔޚ|ᣟⵯ|ᣞﾞ+ﾞꓽ;ʽⰍ(ᠥས(ʺต,ޙเ,ᔊາ,ᠱꓻ,ʹ〳,ྋͺ,ޚᎰ,ۃՙ,ᢜމ,ˑー,ྋͺ,γہ,γہ,ہཐ,ʹ〳,ྋͺ,ޚᎰ,ͺܖ,ᠦས,ۂˉ,މˏ,ʹᱹ,ᠧᱺ,ۂˉ,ߑʻ,ⵗஃ,ᠦⲺ,ᒽހ,ᚔᄾ,ᕐܕ,ⵗஃ,ᠧᱺ,ʹ〳,ྋͺ,ޚᎰ,ۃՙ,ޙเ,ྋͺ,ᖦʹ,ᢜމ,ᵕꜢ,ﾟܚ,ʹ〳,ྋͺ,ޚᎰ,ͺܖ,ͺܖ,ᠦⲺ,ۃՙ,ᖦʹ,γہ,ᖕᒻ,ʾʹ,ʺต,ޙเ,ᔊາ,ᠱꓻ,ʹ〳,ྋͺ,ޚᎰ,ˑー,ۂˉ,ᵕꜢ,ͺܖ,γہ,ˑー,ہཐ,ʹ〳,ྋͺ,ޚᎰ,ͺܖ,ᠦས,ۂˉ,މˏ,ﾟܚ,ʹ〳,ྋͺ,ޚᎰ,ˌˑ,ˌˑ,ۂˉ,ྋͺ,ᠦⲺ,γہ,ہཐ,ʹ〳,ྋͺ,ޚᎰ,ۃՙ,ޙเ,ྋͺ,ᖦʹ,ᢜމ,ᵕꜢ,ᠧᱺ,ᖕᒻ,ʹᱹ,ᠲꓺ,ᠣས,ᚔᄾ,ᐞʹ,ᐠͺ,ᠧᱺ,ˇܘ,ˇܘ,ءᔾ,ᐥヽ,ᖕᒻ,ʾʹ,ᒽހ,ᔊາ,ᢥว,ʾʹ,ʺต,ޙเ,ᔊາ,ᠱꓻ,ʹ〳,ྋͺ,ޚᎰ,ᵕꜢ,ۃՙ,ྋͺ,ᵕꜢ,ˌˑ,ˑー,ہཐ,ᢥˉ,ޢཐ,ޙเ,ᔊາ,މە,ᐠͺ,ᠣˇ,ⵗஃ,ᒽހ,ᠧᱺ,ʹ〳,ྋͺ,ޚᎰ,ˑー,ۂˉ,ᵕꜢ,ͺܖ,γہ,ˑー,ᠧᱺ,ྋͺ,ޚᎰ,ᢜމ,ˌˑ,ᖕᒻ,ᖕᒻ,ꓸە,ྋͺ,ޚᎰ,ˑー,ᔅヾ,ᢥˉ,ޢཐ,ޙเ,ᔊາ,މە,ᐠͺ,ᠣˇ,ⵗஃ,ᒽހ,ᠧᱺ,ʹ〳,ྋͺ,ޚᎰ,ˑー,ۂˉ,ᵕꜢ,ͺܖ,γہ,ˑー,ᠧᱺ,ྋͺ,ޚᎰ,ˌˑ,ᢜމ,ᖕᒻ,ᖕᒻ,ꓸە,ྋͺ,ޚᎰ,ۃՙ,ᔅヾ,ᢥˉ,ޢཐ,ޙเ,ᔊາ,މە,ᐠͺ,ᠣˇ,ⵗஃ,ᒽހ,ᠧᱺ,ʹ〳,ྋͺ,ޚᎰ,ˑー,ۂˉ,ᵕꜢ,ͺܖ,γہ,ˑー,ᠧᱺ,ྋͺ,ޚᎰ,ߑߺ,ۂˉ,ᖕᒻ,ᖕᒻ,ꓸە,ྋͺ,ޚᎰ,މˏ,ᔅヾ,ޢཐ,ޙเ,ᔊາ,މە,ᐠͺ,ᠣˇ,ⵗஃ,ᒽހ,ᠧᱺ,ʹ〳,ྋͺ,ޚᎰ,ˑー,ۂˉ,ᵕꜢ,ͺܖ,γہ,ˑー,ᠧᱺ,ྋͺ,ޚᎰ,ˌˑ,ˌˑ,ᖕᒻ,ᖕᒻ,ꓸە,ྋͺ,ޚᎰ,ͺܖ,ゝܕ,ᠧᱺ,ᢥˉ,ޢཐ,ޙเ,ᔊາ,މە,ᐠͺ,ᠣˇ,ⵗஃ,ᒽހ,ᠧᱺ,ʹ〳,ྋͺ,ޚᎰ,ˑー,ۂˉ,ᵕꜢ,ͺܖ,γہ,ˑー,ᠧᱺ,ྋͺ,ޚᎰ,ᢜމ,ߑߺ,ᖕᒻ,ᖕᒻ,ꓸە,ྋͺ,ޚᎰ,ᵕꜢ,ᖕᒻ,ᔅヾ,ޢཐ,ޙเ,ᔊາ,މە,ᐠͺ,ᠣˇ,ⵗஃ,ᒽހ,ᠧᱺ,ʹ〳,ྋͺ,ޚᎰ,ˑー,ۂˉ,ᵕꜢ,ͺܖ,γہ,ˑー,ᠧᱺ,ྋͺ,ޚᎰ,ᢜމ,ᢜމ,ᖕᒻ,ᖕᒻ,ꓸە,ྋͺ,ޚᎰ,γہ,ゝܕ,ᠧᱺ,ᢥˉ,ޢཐ,ޙเ,ᔊາ,މە,ᐠͺ,ᠣˇ,ⵗஃ,ᒽހ,ᠧᱺ,ʹ〳,ྋͺ,ޚᎰ,ˑー,ۂˉ,ᵕꜢ,ͺܖ,γہ,ˑー,ᠧᱺ,ྋͺ,ޚᎰ,ᢜމ,ͺܖ,ᖕᒻ,ᖕᒻ,ꓸە,ྋͺ,ޚᎰ,ߑߺ,ᖕᒻ,ᔅヾ,ޢཐ,ޙเ,ᔊາ,މە,ᐠͺ,ᠣˇ,ⵗஃ,ᒽހ,ᠧᱺ,ʹ〳,ྋͺ,ޚᎰ,ˑー,ۂˉ,ᵕꜢ,ͺܖ,γہ,ˑー,ᠧᱺ,ྋͺ,ޚᎰ,ˌˑ,ᵕꜢ,ᖕᒻ,ᖕᒻ,ꓸە,ྋͺ,ޚᎰ,ᢜމ,ᔅヾ,ޢཐ,ޙเ,ᔊາ,މە,ᐠͺ,ᠣˇ,ⵗஃ,ᒽހ,ᠧᱺ,ʹ〳,ྋͺ,ޚᎰ,ˑー,ۂˉ,ᵕꜢ,ͺܖ,γہ,ˑー,ᠧᱺ,ྋͺ,ޚᎰ,ᢜމ,މˏ,ᖕᒻ,ᖕᒻ,ꓸە,ྋͺ,ޚᎰ,ˌˑ,ʹᱹ,ᚔᄾ,ۂˉ,ᠧᱺ,ʹ〳,ྋͺ,ޚᎰ,ᵕꜢ,ۃՙ,ྋͺ,ᵕꜢ,ˌˑ,ˑー,ہཐ,ہཐ,ہཐ,ʹ〳,ྋͺ,ޚᎰ,ͺܖ,ͺܖ,ᠦⲺ,ۃՙ,ᖦʹ,γہ,ᖕᒻ,ᠦས,ᔊາ,ᐠͺ,ޙเ,ܪゝ,ʹᱹ,ᐠͺ,ᐞʹ,މە,ᐠͺ,ᠱꓻ,ʹ〳,ྋͺ,ޚᎰ,ˌˑ,ˌˑ,ۂˉ,ྋͺ,ᠦⲺ,γہ,ءᔾ,ᣞᱻ,ޢཐ,ߑʻ,މە,ᠣས,ᣞᱻ,ᐥヽ,ᠧᱺ,ʹ〳,ྋͺ,ޚᎰ,ˌˑ,ˌˑ,ۂˉ,ྋͺ,ᠦⲺ,γہ,ءᔾ,ᣞᱻ,މە,ᠣས,ᚔᄾ,ۂˉ,ᒽހ,ᣞᱻ,ᐥヽ,ᠧᱺ,ᖕᒻ,ᖕᒻ,ʹᱹ,བᵔ,ᠦⲺ,ޙเ,ᒽހ,ᠦⲺ,ᠣས,ᠧᱺ,ʹ〳,ྋͺ,ޚᎰ,ᵕꜢ,ͺܖ,ޙเ,ྋͺ,ྋͺ,ᖦʹ,ᖕᒻ,ʾʹ,ʹ〳,ྋͺ,ޚᎰ,ˌˑ,ˌˑ,ۂˉ,ྋͺ,ᠦⲺ,γہ,ءᔾ,ᣞᱻ,ޢཐ,ߑʻ,މە,ᠣས,ᣞᱻ,ᐥヽ,ᠧᱺ,ʹ〳,ྋͺ,ޚᎰ,ˌˑ,ˌˑ,ۂˉ,ྋͺ,ᠦⲺ,γہ,ءᔾ,ᣞᱻ,މە,ᠣས,ᚔᄾ,ۂˉ,ᒽހ,ᣞᱻ,ᐥヽ,ᠧᱺ,ᖕᒻ,ᖕᒻ,ʹᱹ,བᵔ,བᵔ,བᵔ,ᠧᱺ,ʹ〳,ྋͺ,ޚᎰ,ۃՙ,ᵕꜢ,ྋͺ,ᵕꜢ,ﾟܚ,ྋͺ,ޚᎰ,ˌˑ,ᖦʹ,ޙเ,ˑー,ߑߺ,ᖕᒻ,ﾟܚ,ޙเ,ہཐ,މە,ᕐܕ,ߑʻ,ᔊາ,ᠦⲺ,ᐠͺ,ءᔾ,ʹ〳,ྋͺ,ޚᎰ,ۃՙ,ᢜމ,ˑー,ྋͺ,γہ,γہ,ᠧᱺ,ྋͺ,ޚᎰ,ߑߺ,ޙเ,ᖕᒻ,ᐥヽ,ᠧᱺ,ᖕᒻ,ءᔾ,ʹ〳,ྋͺ,ޚᎰ,ۃՙ,ᢜމ,ˑー,ྋͺ,γہ,γہ,ᠧᱺ,ྋͺ,ޚᎰ,ᢜމ,ᵕꜢ,ᖕᒻ,ᐥヽ,ﾟܚ,ᠦས,ہཐ,ᠤߑ,ޙเ,ʺต,ޙเ,ءᔾ,ʹ〳,ྋͺ,ޚᎰ,ۃՙ,ᢜމ,ˑー,ྋͺ,γہ,γہ,ᠧᱺ,ྋͺ,ޚᎰ,ˌˑ,ˑー,ᖕᒻ,ᐥヽ,ᠧᱺ,މە,ᕐܕ,ߑʻ,ᔊາ,ᠦⲺ,ᐠͺ,ءᔾ,ʹ〳,ྋͺ,ޚᎰ,ۃՙ,ᢜމ,ˑー,ྋͺ,γہ,γہ,ᠧᱺ,ྋͺ,ޚᎰ,ᢜމ,ޙเ,ᖕᒻ,ᐥヽ,ᔅヾ,މە,ᕐܕ,ߑʻ,ᔊາ,ᠦⲺ,ᐠͺ,ءᔾ,ʹ〳,ྋͺ,ޚᎰ,ۃՙ,ᢜމ,ˑー,ྋͺ,γہ,γہ,ᠧᱺ,ྋͺ,ޚᎰ,ˌˑ,ۃՙ,ᖕᒻ,ᐥヽ,ᔅヾ,މە,ᕐܕ,ߑʻ,ᔊາ,ᠦⲺ,ᐠͺ,ءᔾ,ʹ〳,ྋͺ,ޚᎰ,ۃՙ,ᢜމ,ˑー,ྋͺ,γہ,γہ,ᠧᱺ,ྋͺ,ޚᎰ,ߑߺ,ᐠͺ,ᖕᒻ,ᐥヽ,ᖕᒻ,ﾟܚ,ءˋ,ޙเ,ہཐ,މە,ᕐܕ,ߑʻ,ᔊາ,ᠦⲺ,ᐠͺ,ءᔾ,ʹ〳,ྋͺ,ޚᎰ,ۃՙ,ᢜމ,ˑー,ྋͺ,γہ,γہ,ᠧᱺ,ྋͺ,ޚᎰ,ᢜމ,ۃՙ,ᖕᒻ,ᐥヽ,ءᔾ,ʹ〳,ྋͺ,ޚᎰ,ۃՙ,ᢜމ,ˑー,ྋͺ,γہ,γہ,ᠧᱺ,ྋͺ,ޚᎰ,ߑߺ,ᠦⲺ,ᖕᒻ,ᐥヽ,ᠧᱺ,ꓸە,ܯⰍ,ᚲᄾ,ⵗᕀ,ꓸە,ᖕᒻ,ᖕᒻ,ʹᱹ,ޙเ,ˇܘ,ہཐ,ʹ〳,ྋͺ,ޚᎰ,ۃՙ,ᢜމ,ˑー,ྋͺ,γہ,γہ,ᠧᱺ,ྋͺ,ޚᎰ,ᢜމ,ˑー,ᖕᒻ,ᣟꞈ,ᣟꞈ,ᠦས,ˇܘ,ہཐ,ʹ〳,ྋͺ,ޚᎰ,ۃՙ,ᢜމ,ˑー,ྋͺ,γہ,γہ,ᠧᱺ,ྋͺ,ޚᎰ,ᢜމ,ᠦⲺ,ᖕᒻ,ᣟꞈ,ᣟꞈ,ˇܘ,ءˋ,ޙเ,ܯஃ,ᠧᱺ,ᠤߑ,ޙเ,ʺต,ޙเ,ءᔾ,ʹ〳,ྋͺ,ޚᎰ,ۃՙ,ᢜމ,ˑー,ྋͺ,γہ,γہ,ᠧᱺ,ྋͺ,ޚᎰ,ᢜމ,ᐠͺ,ᖕᒻ,ᐥヽ,ᠧᱺ,ʹ〳,ྋͺ,ޚᎰ,ۃՙ,ᢜމ,ˑー,ྋͺ,γہ,γہ,ᠧᱺ,ྋͺ,ޚᎰ,ˌˑ,މˏ,ᖕᒻ,ᔅヾ,ʹ〳,ྋͺ,ޚᎰ,ۃՙ,ᢜމ,ˑー,ྋͺ,γہ,γہ,ᠧᱺ,ྋͺ,ޚᎰ,ߑߺ,ᠦས,ᖕᒻ,ᔅヾ,ʹ〳,ྋͺ,ޚᎰ,ۃՙ,ᢜމ,ˑー,ྋͺ,γہ,γہ,ᠧᱺ,ྋͺ,ޚᎰ,ᢜމ,γہ,ᖕᒻ,ᔅヾ,ʹ〳,ྋͺ,ޚᎰ,ۃՙ,ᢜމ,ˑー,ྋͺ,γہ,γہ,ᠧᱺ,ྋͺ,ޚᎰ,ˌˑ,ߑߺ,ᖕᒻ,ᔅヾ,ʹ〳,ྋͺ,ޚᎰ,ۃՙ,ᢜމ,ˑー,ྋͺ,γہ,γہ,ᠧᱺ,ྋͺ,ޚᎰ,ߑߺ,ᖦʹ,ᖕᒻ,ᔅヾ,ʹ〳,ྋͺ,ޚᎰ,ۃՙ,ᢜމ,ˑー,ྋͺ,γہ,γہ,ᠧᱺ,ྋͺ,ޚᎰ,ᢜމ,ᖦʹ,ᖕᒻ,ᖕᒻ,ﾟܚ,ᔊາ,ہཐ,ʹ〳,ྋͺ,ޚᎰ,ۃՙ,ᢜމ,ˑー,ྋͺ,γہ,γہ,ᠧᱺ,ྋͺ,ޚᎰ,ˌˑ,γہ,ᖕᒻ,ᔅヾ,ʹ〳,ྋͺ,ޚᎰ,ۃՙ,ᢜމ,ˑー,ྋͺ,γہ,γہ,ᠧᱺ,ྋͺ,ޚᎰ,ᢜމ,ۂˉ,ᖕᒻ,ᔅヾ,ʹ〳,ྋͺ,ޚᎰ,ۃՙ,ᢜމ,ˑー,ྋͺ,γہ,γہ,ᠧᱺ,ྋͺ,ޚᎰ,ˌˑ,ͺܖ,ᖕᒻ,ᔅヾ,ʹ〳,ྋͺ,ޚᎰ,ۃՙ,ᢜމ,ˑー,ྋͺ,γہ,γہ,ᠧᱺ,ྋͺ,ޚᎰ,ˌˑ,ྋͺ,ᖕᒻ,ᔅヾ,ʹ〳,ྋͺ,ޚᎰ,ۃՙ,ᢜމ,ˑー,ྋͺ,γہ,γہ,ᠧᱺ,ྋͺ,ޚᎰ,ᢜމ,ᠦས,ᖕᒻ,ﾟܚ,ᔊາ,ہཐ,ᠤߑ,ޙเ,ʺต,ޙเ,ءᔾ,ʹ〳,ྋͺ,ޚᎰ,ۃՙ,ᢜމ,ˑー,ྋͺ,γہ,γہ,ᠧᱺ,ྋͺ,ޚᎰ,ᢜމ,ྋͺ,ᖕᒻ,ᐥヽ,ᠧᱺ,ᔊາ,ᖕᒻ,ᖕᒻ,ܯร,ᔊາ,ہཐ,ᠤߑ,ޙเ,ʺต,ޙเ,ءᔾ,ʹ〳,ྋͺ,ޚᎰ,ۃՙ,ᢜމ,ˑー,ྋͺ,γہ,γہ,ᠧᱺ,ྋͺ,ޚᎰ,ˌˑ,ޙเ,ᖕᒻ,ᐥヽ,ᠧᱺ,ᣞᱻ,ߑʻ,ᣞᱻ,ᖕᒻ,ʹᱹ,ۂˉ,ߑʻ,ⵗஃ,ᠦⲺ,ᒽހ,ᚔᄾ,ᕐܕ,ⵗஃ,ᠱꓻ,ʹ〳,ྋͺ,ޚᎰ,ͺܖ,ᠦས,ۂˉ,މˏ,ᠧᱺ,ʹ〳,ྋͺ,ޚᎰ,ͺܖ,ˌˑ,γہ,ྋͺ,މˏ,ᐠͺ,ﾟܚ,ʹ〳,ྋͺ,ޚᎰ,ˑー,ۂˉ,ۂˉ,ᠦⲺ,މˏ,ᵕꜢ,ᖕᒻ,ʾʹ,ʺต,ޙเ,ᔊາ,ᠱꓻ,ʹ〳,ྋͺ,ޚᎰ,ۃՙ,ᵕꜢ,ྋͺ,ᵕꜢ,ᠦⲺ,ˌˑ,ہཐ,ʹ〳,ྋͺ,ޚᎰ,ۃՙ,ᵕꜢ,ྋͺ,ᵕꜢ,ᠧᱺ,ᖕᒻ,ʹᱹ,ᔊາ,ᐠͺ,ᒽހ,ߑʻ,ᔊາ,ⵗஃ,ᠱꓻ,ʹ〳,ྋͺ,ޚᎰ,ͺܖ,ᠦས,ۂˉ,މˏ,ہཐ,ۂˉ,ߑʻ,ⵗஃ,ᠦⲺ,ᒽހ,ᚔᄾ,ᕐܕ,ⵗஃ,ᠧᱺ,ʹ〳,ྋͺ,ޚᎰ,ͺܖ,ᠦས,ۂˉ,މˏ,ˌˑ,މˏ,ﾟܚ,ʹ〳,ྋͺ,ޚᎰ,ˑー,ˑー,ͺܖ,ޙเ,ᵕꜢ,ᵕꜢ,ᖕᒻ,ʾʹ,ʹ〳,ྋͺ,ޚᎰ,ͺܖ,ᠦས,ۂˉ,މˏ,ˌˑ,މˏ,ہཐ,ʹ〳,ྋͺ,ޚᎰ,ͺܖ,ᠦས,ۂˉ,މˏ,ˌˑ,މˏ,ᢥˉ,ྋͺ,ޚᎰ,ߑߺ,ޙเ,ʹᱹ,ʺต,ޙเ,ᔊາ,ᠱꓻ,ʹ〳,ྋͺ,ޚᎰ,ˑー,ᠦⲺ,ˌˑ,ᐠͺ,ۃՙ,ˌˑ,ہཐ,ʹ〳,ྋͺ,ޚᎰ,ۃՙ,ᵕꜢ,ྋͺ,ᵕꜢ,ᠦⲺ,ˌˑ,ءᔾ,ʹ〳,ྋͺ,ޚᎰ,ͺܖ,ᠦས,ۂˉ,މˏ,ˌˑ,މˏ,ᐥヽ,ʹᱹ,ᔊາ,ᐠͺ,ᒽހ,ߑʻ,ᔊາ,ⵗஃ,ᠱꓻ,ʹ〳,ྋͺ,ޚᎰ,ˑー,ᠦⲺ,ˌˑ,ᐠͺ,ۃՙ,ˌˑ,ʹᱹ,བᵔ,ﾟܚ,ʹ〳,ྋͺ,ޚᎰ,ͺܖ,ᠦས,ۂˉ,މˏ,ᠧᱺ,ʹ〳,ྋͺ,ޚᎰ,ͺܖ,ˌˑ,γہ,ྋͺ,މˏ,ᐠͺ,ﾟܚ,ʹ〳,ྋͺ,ޚᎰ,ˑー,ۂˉ,ۂˉ,ᠦⲺ,މˏ,ᵕꜢ,ᖕᒻ,ʹᱹ,བᵔ,ᔊາ,ʹᱹ,ۂˉ,ߑʻ,ⵗஃ,ᠦⲺ,ᒽހ,ᚔᄾ,ᕐܕ,ⵗஃ,ᠱꓻ,ʹ〳,ྋͺ,ޚᎰ,ۃՙ,ᵕꜢ,ྋͺ,ᵕꜢ,ᠧᱺ,ᖕᒻ,ʾʹ,ʺต,ޙเ,ᔊາ,ᠱꓻ,ʹ〳,ྋͺ,ޚᎰ,މˏ,ᵕꜢ,ᖦʹ,ޙเ,ᖦʹ,މˏ,ہཐ,ءᔾ,ᣞᱻ,ᢥˉ,ᢥˉ,ᢥˉ,ᢥˉ,ᠴހ,ᡟᒽ,ᠧܪ,ᒡꓹ,ᕐᱺ,ㆴꧦ,ˆᐝ,ᣞʻ,ᐝꓻ,ܙ〵,ᒼᓐ,ᢥˉ,ᢥˉ,ᢥˉ,ᢥˉ,ʻゝ,ޚᎰ,ྋͺ,ޙเ,ᣞᱻ,ﾟܚ,ᣞᱻ,ᵕꜢ,ྋͺ,ᵕꜢ,γہ,ͺܖ,ྋͺ,ᵕꜢ,ᢜๅ,ܪݥ,ᢦߴ,ᠦⲺ,ᠦས,ᢥว,ᣞᱻ,ﾟܚ,ᣞᱻ,ᵕꜢ,ˌˑ,ͺܖ,ܪゝ,ᒽހ,މە,ꓼߵ,ۂˉ,ᕐܕ,ᣞᱻ,ﾟܚ,ᣞᱻ,ͺܖ,ͺܖ,ߑߺ,ͺܖ,ྋͺ,މˏ,ᠩᓐ,ˇܖ,ᠲꓺ,ᠣས,ᢥว,ᐞʹ,ᣞᱻ,ﾟܚ,ᣞᱻ,ᐞʹ,ᕐܕ,ᕝด,ᚔᄾ,ⵗஃ,ᕝˑ,ᚔᄾ,ᣞᱻ,ﾟܚ,ᣞᱻ,ᢥˉ,ᢥˉ,ᢥˉ,ᢥˉ,ᢥˉ,ᢥˉ,ᢥˉ,ᢥˉ,ᢥˉ,ᢥˉ,ㆴꧦ,ˆᐝ,ۃட,ངו,ⴰʹ,ᠧᱺ,ᐠݚ,ܖเ,ⴰʹ,ᖕᒻ,ᒡꓹ,ˑー,ྋͺ,މˏ,ˌˑ,ߑߺ,ͺܖ,ˌˑ,ۃՙ,ᢜމ,މˏ,ᢥˉ,ᢥˉ,ᢥˉ,ᢥˉ,ᢥˉ,ᢥˉ,ᢥˉ,ᢥˉ,ᢥˉ,ᢥˉ,ᣞᱻ,ﾟܚ,ᣞᱻ,ۂˉ,ͺܖ,ᖦʹ,ᵕꜢ,ᢜމ,ᠦས,ۂˉ,ۂˉ,ᐠͺ,މˏ,ᢜމ,ᐠͺ,ᠦས,ᖦʹ,ᐠͺ,މˏ,ˌˑ,ྋͺ,ۂˉ,ˌˑ,ˌˑ,ˑー,ۃՙ,ۂˉ,ᢜމ,ᵕꜢ,ˌˑ,ˑー,ᠦས,ˑー,ᠦⲺ,ᠦⲺ,ᣞᱻ,ﾟܚ,ᣞᱻ,ㆴꧦ,ˆᐝ,ۃட,ངו,ⴰʹ,ᠧᱺ,ᐠݚ,ܖเ,ⴰʹ,ᖕᒻ,ᒡꓹ,ˑー,ྋͺ,މˏ,ˌˑ,ߑߺ,ͺܖ,ˌˑ,ۃՙ,ᢜމ,މˏ,ᣞᱻ,ﾟܚ,ᣞᱻ,ᒽހ,ᕐܕ,ޙเ,މە,ᒽހ,ᣞᱻ,ﾟܚ,ᣞᱻ,ᢥˉ,ᢥˉ,ᢥˉ,ᢥˉ,ᢥˉ,ᢥˉ,ᢥˉ,ᢥˉ,ᢥˉ,ᢥˉ,ᢥˉ,ᢥˉ,ͺˑ,ﾟꜢ,ᠷᑊ,ᖦߪ,ˆᐝ,ⵂⲲ,ㆵہ,ᒡꓹ,ܯⰍ,ᚲᄾ,ⵗᕀ,ͺˑ,ᢥˉ,ᢥˉ,ᢥˉ,ᢥˉ,ᢥˉ,ᢥˉ,ᢥˉ,ᢥˉ,ᢥˉ,ᢥˉ,ᢥˉ,ᢥˉ,ʻゝ,ޚᎰ,ྋͺ,ޙเ,ᣞᱻ,ﾟܚ,ᣞᱻ,ᢥˉ,ᢥˉ,ᢥˉ,ᢥˉ,ᢥˉ,ᢥˉ,ᢥˉ,ᢥˉ,ᢥˉ,ᢥˉ,ᢥˉ,ᢥˉ,ᕐᱺ,ˆᐝ,ˆᐝ,ꓹᑉ,ㆍำ,ᕐⲲ,ᱹᒽ,ᒡꓹ,ᒽހ,ޙเ,ᕐܕ,ᠦས,ޙเ,ᚔܢ,ᠦⲺ,ۂˉ,ᢥˉ,ᢥˉ,ᢥˉ,ᢥˉ,ᢥˉ,ᢥˉ,ᢥˉ,ᢥˉ,ᢥˉ,ᢥˉ,ʻゝ,ޚᎰ,ྋͺ,ޙเ,ᣞᱻ,ﾟܚ,ᣞᱻ,ءˋ,ᖦʹ,ᵕꜢ,ᠲང,ⵗஃ,ᠦⲺ,ᕐܕ,ᖦʹ,ᐠͺ,ᣞᱻ,ﾟܚ,ᣞᱻ,ᠦས,ᕐܕ,ᕐܕ,ܪゝ,ꞈމ,ᕐܕ,ߑʻ,ᔊາ,ᠦⲺ,ᐠͺ,ᕝˑ,ᔊາ,ᐞʹ,ᣞᱻ,ﾟܚ,ᣞᱻ,ʻゝ,ޚᎰ,ྋͺ,ޙเ,ᢥˉ,ᢥˉ,ᢥˉ,ᢥˉ,ٴߑ,ᕐᄼ,ޚๅ,ᱺᅳ,ᶥೲ,ᠹʺ,ꓻˊ,ᠧⵯ,ㆴꧦ,ˆᐝ,ᢥˉ,ᢥˉ,ᢥˉ,ᢥˉ,ʻゝ,ޚᎰ,ྋͺ,ޙเ,ᣞᱻ,ﾟܚ,ᣞᱻ,ᢥˉ,ᢥˉ,ᠴހ,ᡟᒽ,ᠧܪ,ᒡꓹ,ᕐᱺ,ㆴꧦ,ˆᐝ,ᣞʻ,ᐝꓻ,ܙ〵,ᒼᓐ,ﾟܚ,ᠹˇ,ᣞས,ꓽꜤ,ᛍܝ,ᒼᓐ,ۃᔾ,ꓸᓐ,ٴᱻ,ꜙเ,ꓽꜤ,າߺ,ʽະ,ᕐᄼ,ᢥˉ,ᢥˉ,ʻゝ,ޚᎰ,ྋͺ,ޙเ,ᣞᱻ,ﾟܚ,ᣞᱻ,γہ,މˏ,މˏ,ߑߺ,ۃՙ,γہ,ͺܖ,ᢥว,ᢜๅ,ᐧܢ,ܪゝ,ᔈߴ,ᠩᓐ,ᣞᱻ,ﾟܚ,ᣞᱻ,ʻゝ,ޚᎰ,ྋͺ,ޙเ,ᢥˉ,ᢥˉ,ᢥˉ,ᢥˉ,ᢥˉ,ᢥˉ,ᢥˉ,ᢥˉ,ᢥˉ,ᢥˉ,ᢥˉ,ᢥˉ,ٴߑ,ᕐᄼ,ޚๅ,ᱺᅳ,ᶥೲ,ᠹʺ,ꓻˊ,ᠧⵯ,ㆴꧦ,ˆᐝ,ᢥˉ,ᢥˉ,ᢥˉ,ᢥˉ,ᢥˉ,ᢥˉ,ᢥˉ,ᢥˉ,ᢥˉ,ᢥˉ,ᢥˉ,ᢥˉ,ʻゝ,ޚᎰ,ྋͺ,ޙเ,ᣞᱻ,ﾟܚ,ᣞᱻ,ᢥˉ,ᢥˉ,ᢥˉ,ᢥˉ,ᠹˇ,ᣞས,ꓽꜤ,ᛍܝ,ᒼᓐ,ۃᔾ,ꓸᓐ,ٴᱻ,ꜙเ,ꓽꜤ,າߺ,ʽະ,ᕐᄼ,ᢥˉ,ᢥˉ,ᢥˉ,ᢥˉ,ʻゝ,ޚᎰ,ྋͺ,ޙเ,ᣞᱻ,ﾟܚ,ᣞᱻ,ˑー,ྋͺ,ˑー,ˑー,ᵕꜢ,ᢜމ,ྋͺ,ہː,ᢦߴ,ޙเ,ᢦߴ,ۀᐥ,ۀᐥ,ᣞᱻ,ﾟܚ,ᣞᱻ,ͺܖ,ꞈމ,ˈꓻ,ᚔᄾ,ᠦՙ,ᔈߴ,ᢜๅ,ᣞᱻ,ﾟܚ,ᣞᱻ,ᕝด,ᐠͺ,ᒽހ,ᣞᱻ,ﾟܚ,ᣞᱻ,ᕝด,ᐠͺ,ᒽހ,ᢜๅ,ᕐܕ,ᕝด,ᚔᄾ,ⵗஃ,ᠣˇ,ⵗஃ,ۂˉ,ᕐܕ,ᠱⵯ,ޙเ,ޢཐ,ᣞᱻ,ﾟܚ,ᣞᱻ,ᢥˉ,ᢥˉ,ᢥˉ,ᢥˉ,ͺˑ,ﾟꜢ,ᠷᑊ,ᖦߪ,ˆᐝ,ⵂⲲ,ㆵہ,ᒡꓹ,ܯⰍ,ᚲᄾ,ⵗᕀ,ͺˑ,ᢥˉ,ᢥˉ,ᢥˉ,ᢥˉ,ʻゝ,ޚᎰ,ྋͺ,ޙเ,ᣞᱻ,ﾟܚ,ᣞᱻ,ءˋ,ޙเ,ᒽހ,ᠦⲺ,ᠣས,ᣞᱻ,ﾟܚ,ᣞᱻ,ᢥˉ,ᢥˉ,ᢥˉ,ᢥˉ,ᕐᱺ,ˆᐝ,ˆᐝ,ꓹᑉ,ㆍำ,ᕐⲲ,ᱹᒽ,ᒡꓹ,ᒽހ,ޙเ,ᕐܕ,ᠦས,ޙเ,ᚔܢ,ᠦⲺ,ۂˉ,ᢥˉ,ᢥˉ,ᢥˉ,ᢥˉ,ʻゝ,ޚᎰ,ྋͺ,ޙเ,ᣞᱻ,ﾟܚ,ᣞᱻ,ᠦས,ᕐܕ,ᕐܕ,ܪゝ,ꞈމ,ᕐܕ,ߑʻ,ᔊາ,ᠦⲺ,ᐠͺ,ⵂߺ,ޙเ,ءˋ,ᐠͺ,ᣞᱻ,ﾟܚ,ᣞᱻ,ˑー,ᢜމ,ྋͺ,ᵕꜢ,ˑー,މˏ,މˏ,ᠲང,ޚݥ,ޚᎰ,ᠲꓺ,ᖦʹ,ᠲꓺ,ᣞᱻ,ﾟܚ,ᣞᱻ,ᐞʹ,ᕐܕ,ᕝด,ᣞᱻ,ﾟܚ,ᣞᱻ,ܯⰍ,ᚲᄾ,ⵗᕀ,ᣞᱻ,ﾟܚ,ᣞᱻ,ᠦས,ᕐܕ,ᕐܕ,ܪゝ,ꞈމ,ᕐܕ,ߑʻ,ᔊາ,ᠦⲺ,ᐠͺ,ހᐨ,ᕐܕ,ءˋ,ءˋ,ᐠͺ,ⵗஃ,ᒽހ,ᣞᱻ,ﾟܚ,ᣞᱻ,މˏ,ۃՙ,ˌˑ,ˌˑ,މˏ,ˌˑ,މˏ,ߑߺ,ᠸว,ᠲང,ᠤߑ,ᕝด,ᠣˇ,ޢཐ,ᣞᱻ,ﾟܚ,ᣞᱻ,ᢜމ,ᢜމ,ˑー,ۃՙ,މˏ,ހᐨ,ޙเ,ᵕߪ,ޚݥ,ᐧܢ,ꧦᎱ,ᣞᱻ,ﾟܚ,ᣞᱻ,ܙ〵,ᒼᓐ,ㆴꧦ,ˆᐝ,ﾟꜢ,ᠷᑊ,ᖦߪ,ˆᐝ,ⵂⲲ,ㆵہ,ᣞᱻ,ᐥヽ,ʹᱹ,ʹ〳,ྋͺ,ޚᎰ,ۃՙ,ᵕꜢ,ྋͺ,ᵕꜢ,ہཐ,ۂˉ,ߑʻ,ⵗஃ,ᠦⲺ,ᒽހ,ᚔᄾ,ᕐܕ,ⵗஃ,ᠧᱺ,ᖕᒻ,ʾʹ,ᔊາ,ᐠͺ,ᒽހ,ߑʻ,ᔊາ,ⵗஃ,ᠱꓻ,ʹ〳,ྋͺ,ޚᎰ,މˏ,ᵕꜢ,ᖦʹ,ޙเ,ᖦʹ,މˏ,ʹᱹ,བᵔ,ʹᱹ,ᔊາ,ᐠͺ,ᒽހ,ߑʻ,ᔊາ,ⵗஃ,ᠱꓻ,ʹ〳,ྋͺ,ޚᎰ,ۃՙ,ᵕꜢ,ྋͺ,ᵕꜢ,ᠧᱺ,ᖕᒻ,ʹᱹ,བᵔ))})();r\n</js>\n$.data[*]",
      "bookUrl": "$.surl",
      "checkKeyWord": "华娱之摄影",
      "coverUrl": "$.cover",
      "intro": "$.description",
      "kind": "",
      "lastChapter": "",
      "name": "$.title",
      "wordCount": ""
    },
    "ruleToc": {
      "chapterList": "@js:\nif (baseUrl.match(/69shuba/)){\nlet o = java.getElement('.catalog:last-child>ul>li')\nlet aid = java.getString('aid')\nif(aid!=''){\n\tlet items = java.getElement('items')\n\to = []\n\tfor(v of Object.values(items)){\n\t\tlet href = java.get('path')+aid+'/'+v.cid+java.get('tp')\n\t\thref = completeUrl(href, baseUrl)\n\t\to.push({text:v.n,href:href})\n\t}\n}else{\n\tlet use = {}, offset = 0\n\tArray.from(o).filter(v=>v.hasAttr('data-num')).sort((a,b)=>a.attr('data-num')-b.attr('data-num')).map((v, i)=>{if(!use[v.attr('data-num')]){o[i-offset]=v.select('a')[0];use[v.attr('data-num')]=true}else{o.remove(i-offset);offset++}})\n}o\n}else {\n\ta=Array.from(java.getElements('.zjbox@ul@li@a'))\n\tb=a.reverse()\n\t}",
      "chapterName": "text##^\\d+\\.|（.*合.*|（含.*|\\(.*合.*|\\(含.*\n@js:result\n.replace(\"••\",\"\")\n.replace(/^(\\d+).第/,'第')\n.replace(/【\\d+】/,'')\n.replace(/^(正文|VIP章节|最新章节)?(\\s+|_)|[\\(\\{（｛【].*[求含理更谢乐发推票盟补加字Kk\\/].*/g,'')\n.replace(/^(\\d+)[、．]第.+章/,'第$1章')\n.replace(/^(\\d+)、\\d+、/,'第$1章 ')\n.replace(/^(\\d+)、\\d+/,'第$1章')\n.replace(/^(第.+章)\\s?\\d+/,'$1')\n.replace(/^(\\d+)、/,'第$1章 ')\n.replace(/^(第.+章)\\s?第.+章/,'$1')\n.replace(/第\\s(.+)\\s章/,'第$1章')\n.replace(/.*(chapter|Chapter)\\s?(\\d+)\\s?/,'$1 $2 ')\n.replace(/\\(.+\\)/,'')\n.replace(/\\[|。/,'')\n.replace(/第([零一二两三四五六七八九十百千]+)章/g,java.toNumChapter(result))\n##(章)([^\\s]+)(\\s·)##$1 $2$3",
      "chapterUrl": "href\n@js:completeUrl(result, baseUrl)",
      "preUpdateJs": ""
    },
    "searchUrl": "<js>\n(()=>{var བʺ='ܝـ'&'ᠫܪ',ˑߺ=-~'ᠹܪ',ᒽˋ=ˑߺ-~'ᡍߵ',ᠫˊ=ᒽˋ+ᒽˋ,ᱺۃ=ᠫˊ*ᒽˋ,ᠣˇ=ᒽˋ*ᠫˊ*ᒽˋ,ངๅ=ᱺۃ*ᠫˊ,ᔅʾ=ᠫˊ*ᠣˇ,ᖕߑ=ᱺۃ*ᒽˋ*ᱺۃ,བߑ=ᔅʾ*ᠫˊ,ᒻﾞ=ᱺۃ*ᔅʾ,ꜗᱻ=ᠫˊ*བߑ,ˑˊ=ᔅʾ*ངๅ,ʹۀ=བߑ*ᠣˇ,ۂܢ=ᱺۃ*ꜗᱻ,ہߺ=ངๅ*ᒻﾞ,ᐝⲺ=ᠫˊ*ۂܢ,ᠢະ=!ˑߺ+[],ངי=ᠢະ[བʺ],ᔅᄾ=ངי[ˑߺ]+[],ᚒᐨ=ᠢະ[ˑߺ],ᒼꜢ=ᠢະ[ᒽˋ],ᱸᎰ=ᠢະ[ᒽˋ+ˑߺ],ᠸᅳ=ᠢະ[ᠫˊ],ˌⲲ=ᔅᄾ[ᠫˊ+ˑߺ],ⵆˈ=[]+{},ᢤہ=ⵆˈ[ᠫˊ+ˑߺ],γᆞ=ⵆˈ[ᒽˋ],ⵗᵔ=ᔅᄾ[བʺ],ᐥᎱ=ᔅᄾ[ˑߺ],ⵗᒼ=(!བʺ+[])[བʺ],ᔾᆢ=ⵆˈ[ˑߺ],ᔉߴ=ⵆˈ[ᱺۃ-ˑߺ],ⴰʺ=ᔅᄾ[ᒽˋ],ꓽހ=(!བʺ+[])[ˑߺ],ㆴʹ=ᢤہ+ᔾᆢ+ᐥᎱ+ᱸᎰ+ⵗᒼ+ꓽހ+ⵗᵔ+ᢤہ+ⵗᒼ+ᔾᆢ+ꓽހ,ᖮݥ=[][ངי+ˌⲲ+ᒼꜢ+ⵗᒼ+ᠸᅳ+ꓽހ],ᡟཐ=ᖮݥ[ㆴʹ],ᠸʹ=''[ㆴʹ]+[],ꧦཕ=ᠸʹ[ˑߺ+ᱺۃ],יޙ=ᠸʹ[ᠣˇ-ᒽˋ],ᠲﾟ=ⵗᒼ+ᔾᆢ+ꧦཕ+ⵗᒼ+ꓽހ+ˌⲲ+ᐥᎱ+יޙ,ⵈⲺ=(ˑߺ+ᱺۃ+ᠣˇ)[ᠲﾟ](ངๅ),ⴰˏ=[][ㆴʹ][ㆴʹ](ꓽހ+ᠸᅳ+ⵗᒼ+ⵗᵔ+ꓽހ+ᐥᎱ+ᔉߴ+ᠸᅳ+ᱸᎰ+ᢤہ+ᚒᐨ+ⵈⲺ+ᠸᅳ)(),ᱹས=ⴰˏ(''[γᆞ+ˌⲲ+יޙ]())[ᒽˋ],ᔉމ=(ᠣˇ+ᠫˊ+ᒽˋ)[ᠲﾟ](ངๅ),އʻ=(ᠣˇ+ˑߺ)[ᠲﾟ](ངๅ),ꜙޙ=(ངๅ-ˑߺ)[ᠲﾟ](ངๅ),ⵂݦ=''[ㆴʹ][ངי+ꓽހ+ᔾᆢ+ᔉމ+ᱹས+އʻ+ᚒᐨ+ꓽހ+ᱹས+ᔾᆢ+ⴰʺ+ᠸᅳ],ᠷᱹ=ᡟཐ(ꓽހ+ᠸᅳ+ⵗᒼ+ⵗᵔ+ꓽހ+ᐥᎱ+ᔉߴ+ᠸᅳ+ꜙޙ+ᚒᐨ+ᒼꜢ)(),ᠫܕ=ᠣˇ|ᒽˋ|ᱺۃ+ངๅ,ᱼᱺ=ᔅʾ+ངๅ+ᠫˊ,ەⰍ=ᔅʾ|ˑߺ|ᒽˋ|ངๅ,ⵈᒾ=ᱺۃ+ᠫˊ|ངๅ,ᢦᒻ=ངๅ|ᱺۃ|ᠣˇ,ᱹܘ=ᠫˊ|ᒽˋ|ངๅ|ᱺۃ+ˑߺ,ޣˋ=ᔅʾ+ᠫˊ|ˑߺ+ᱺۃ,ᕐہ=ངๅ,ٴา=ᔅʾ+ˑߺ+ᠣˇ+ᠫˊ+ᒽˋ,ܙเ=ˑߺ|ᠣˇ+ᱺۃ|ᔅʾ|ᒽˋ,ᛍꓸ=ངๅ|ᠫˊ+ᠣˇ|ᔅʾ+ˑߺ|ᱺۃ,ꙿˏ=ᒽˋ+ᠫˊ|ᔅʾ|ངๅ,ᑉᐩ=ˑߺ|ᱺۃ+ᔅʾ,اۃ=ᠫˊ|ᠣˇ+ངๅ,ᠥߴ=ᠫˊ+ᒽˋ+ᔅʾ+ᱺۃ|ངๅ,ᖦเ=ངๅ|ᒽˋ+ᱺۃ,ㆵꜤ=ᒽˋ|ˑߺ|ᠫˊ|ངๅ+ᠣˇ,އء=ངๅ|ᒽˋ|ᔅʾ,ⵓถ=ᱺۃ|ᔅʾ+ངๅ,ㆵʹ=ᒽˋ|ᠣˇ|ངๅ,ᠶา=ᱺۃ+ᔅʾ,ⴰߪ=ངๅ|ᔅʾ+ᱺۃ|ᠣˇ,ᢏݚ=ᠣˇ+ᒽˋ+ᔅʾ,ʿˌ=ᱺۃ+ᠫˊ+ᔅʾ,ᛧꞋ=ᱺۃ|ངๅ+ᠣˇ+ᔅʾ+ˑߺ,ᐠต=ᠫˊ+ᔅʾ|ˑߺ|ངๅ+ᱺۃ+ᒽˋ,ᠶᎱ=ངๅ+ᠫˊ+ˑߺ+ᠣˇ,ʿˏ=ˑߺ+ངๅ,ⵆޚ=ᔅʾ+ˑߺ+ངๅ,ᡍⲲ=ᠣˇ|ᱺۃ|ངๅ|ˑߺ,ᚒᒾ=ᱺۃ|ᠫˊ|ˑߺ|ᠣˇ|ᒽˋ|ངๅ,ꓸꧦ=ᠣˇ+ངๅ,ᱺˉ=ᱺۃ|ˑߺ+ᠫˊ|ᔅʾ|ངๅ,ͺⲲ=ᠫˊ+ᔅʾ|ᠣˇ|ངๅ+ᒽˋ,ޙᡃ=ངๅ|ˑߺ|ᒽˋ|ᱺۃ,ᒡˋ=ᔅʾ+ᒽˋ,ᢥᄼ=ᱺۃ|ᒽˋ|ᠣˇ|ᔅʾ,ˆᄾ=ᱺۃ|ངๅ|ᔅʾ|ᒽˋ,ʹꓼ=ངๅ|ᠫˊ+ᒽˋ+ᱺۃ,ᐥː=ᒽˋ|ངๅ|ᔅʾ|ᠫˊ|ˑߺ,ʹۃ=ᠣˇ|ᱺۃ|ᠫˊ+ᔅʾ+ˑߺ,ᔅ〵=ᠫˊ|ᔅʾ,ᠫᑊ=ᠫˊ+ˑߺ+ᔅʾ+ངๅ|ᠣˇ,ᒡꙿ=ᒽˋ+ᠫˊ|ᱺۃ+ᔅʾ,ꞈร=ᔅʾ|ᒽˋ|ᠫˊ,ᛍᄾ=ˑߺ|ᔅʾ|ᱺۃ+ᒽˋ|ᠫˊ+ᠣˇ,ᢏང=ᔅʾ+ᠣˇ|ᒽˋ|ངๅ|ˑߺ,ᓪه=ˑߺ|ངๅ+ᱺۃ|ᠫˊ,ᔇˇ=ᔅʾ|ᠫˊ+ˑߺ+ᠣˇ,ހߴ=ᠫˊ|ངๅ|ᒽˋ+ˑߺ,ﾟஃ=ᠣˇ|ངๅ+ˑߺ,ᣟʾ=ˑߺ|ᔅʾ|ᒽˋ,ᖕꙿ=ངๅ|ᒽˋ|ᠣˇ+ᔅʾ,ܪߪ=ᒽˋ+ᱺۃ+ངๅ|ᔅʾ|ᠣˇ,ᠸՙ=ᠣˇ+ᠫˊ+ᔅʾ,ޚว=ᱺۃ|ˑߺ|ᔅʾ+ངๅ,ʾˬ=ᠣˇ|ᔅʾ+ˑߺ,ܪˑ=ངๅ+ᠣˇ+ᒽˋ+ˑߺ,اʹ=ᠫˊ+ˑߺ+ᔅʾ|ངๅ,ᠲゝ=ˑߺ|ᔅʾ,ᢦˆ=ངๅ+ᠣˇ|ˑߺ|ᒽˋ|ᱺۃ,ᓒܢ=ᠣˇ|ངๅ|ᔅʾ|ᒽˋ|ˑߺ+ᠫˊ,ᛧޚ=ᔅʾ|ངๅ|ᠣˇ+ˑߺ,ꜘ〳=ངๅ|ᠫˊ+ᠣˇ|ᒽˋ,ˈܙ=ᒽˋ|ᱺۃ|ˑߺ+ᠣˇ+ᔅʾ|ངๅ,ᕝヾ=ངๅ+ᠫˊ|ᔅʾ+ᱺۃ,ܙས=ངๅ+ᔅʾ+ˑߺ|ᱺۃ|ᒽˋ,ᐠᱻ=ᠫˊ+ངๅ+ᱺۃ+ˑߺ+ᠣˇ,ᒢᆞ=ᒽˋ|ᠫˊ+ངๅ,ˈང=ᱺۃ|ངๅ,ᐟถ=ᠫˊ|ᔅʾ+ᒽˋ+ˑߺ,ᣞꓸ=ᠣˇ+ངๅ|ᠫˊ|ᔅʾ,ᠢۂ=ᔅʾ|ᠣˇ+ངๅ,ᐝᱺ=ངๅ+ˑߺ|ᱺۃ;ᠷᱹ(ⵂݦ(ͺⲲ,ⵆޚ,ᖕꙿ,ᕐہ,ᛍᄾ,ꓸꧦ,ⴰߪ,ᠶᎱ,ᡍⲲ,ᢦᒻ,اʹ,ᡍⲲ,ꙿˏ,ᐠᱻ,ᛍᄾ,ꓸꧦ,ⴰߪ,اۃ,اۃ,ەⰍ,އء,ᢦˆ,ꙿˏ,ᠫᑊ,ᠥߴ,ەⰍ,ᣞꓸ,ޚว,ᐠต,ᠥߴ,ᕐہ,ᛍᄾ,ꓸꧦ,ⴰߪ,اۃ,اۃ,ەⰍ,އء,ˈང,ᛍᄾ,ꓸꧦ,ⴰߪ,اۃ,ᢦᒻ,އء,اۃ,اۃ,اۃ,ⵈᒾ,ᛍᄾ,ꓸꧦ,ⴰߪ,اۃ,اʹ,ܪˑ,ﾟஃ,ㆵʹ,ᢦᒻ,ᐝᱺ,ˈܙ,ͺⲲ,ⵆޚ,ᖕꙿ,ᕐہ,ᛍᄾ,ꓸꧦ,ⴰߪ,ەⰍ,ꙿˏ,ﾟஃ,ꜘ〳,ꜘ〳,اʹ,ᐠᱻ,ᛍᄾ,ꓸꧦ,ⴰߪ,ەⰍ,ꙿˏ,ﾟஃ,ꜘ〳,ˈང,ᐝᱺ,ᢦˆ,ᖕꙿ,اʹ,ᣞꓸ,ᠫᑊ,ᖕꙿ,ᠥߴ,ᕐہ,ᛍᄾ,ꓸꧦ,ⴰߪ,اۃ,اۃ,ەⰍ,އء,ᐠᱻ,ꙿˏ,ᠫᑊ,ᠥߴ,ەⰍ,ᣞꓸ,ޚว,ᐠต,ᠥߴ,ˈང,ᛍᄾ,ꓸꧦ,ⴰߪ,اۃ,اۃ,ەⰍ,އء,ㆵʹ,ەⰍ,ⵈᒾ,ᛍᄾ,ꓸꧦ,ⴰߪ,ᱼᱺ,އء,ᡍⲲ,اʹ,އء,ⵆޚ,ᐝᱺ,ˈܙ,ᛍᄾ,ꓸꧦ,ⴰߪ,اۃ,اۃ,ەⰍ,އء,ㆵʹ,ەⰍ,ᐠᱻ,ᛍᄾ,ꓸꧦ,ⴰߪ,اۃ,اۃ,ەⰍ,އء,ㆵʹ,ەⰍ,ᓪه,ꓸꧦ,ⴰߪ,اʹ,ᠶᎱ,ᢦˆ,ͺⲲ,ⵆޚ,ᖕꙿ,ᕐہ,ᛍᄾ,ꓸꧦ,ⴰߪ,ﾟஃ,ܪˑ,ᡍⲲ,އء,ﾟஃ,ᠶᎱ,ᐠᱻ,ᛍᄾ,ꓸꧦ,ⴰߪ,ەⰍ,ꙿˏ,ﾟஃ,ꜘ〳,ꜘ〳,اʹ,ܙเ,ᛍᄾ,ꓸꧦ,ⴰߪ,اۃ,اۃ,ەⰍ,އء,ㆵʹ,ەⰍ,ʹۃ,ᢦˆ,ᖕꙿ,اʹ,ᣞꓸ,ᠫᑊ,ᖕꙿ,ᠥߴ,ᕐہ,ᛍᄾ,ꓸꧦ,ⴰߪ,ﾟஃ,ܪˑ,ᡍⲲ,އء,ﾟஃ,ᠶᎱ,ᢦˆ,ᛍꓸ,ⵈᒾ,ᛍᄾ,ꓸꧦ,ⴰߪ,اۃ,اۃ,ەⰍ,އء,ˈང,ᛍᄾ,ꓸꧦ,ⴰߪ,اۃ,ᢦᒻ,އء,اۃ,اۃ,اۃ,ⵈᒾ,ᛍᄾ,ꓸꧦ,ⴰߪ,اۃ,اʹ,ܪˑ,ﾟஃ,ㆵʹ,ᢦᒻ,ᐝᱺ,ᢦˆ,ᛍꓸ,ꙿˏ,ᠫᑊ,ᠥߴ,ەⰍ,ᣞꓸ,ޚว,ᐠต,ᠥߴ,ᕐہ,ᛍᄾ,ꓸꧦ,ⴰߪ,ەⰍ,ꙿˏ,ﾟஃ,ꜘ〳,ˈང,ᐝᱺ,ˈܙ,ͺⲲ,ⵆޚ,ᖕꙿ,ᕐہ,ᛍᄾ,ꓸꧦ,ⴰߪ,ㆵʹ,ܪˑ,اʹ,ꙿˏ,ᠶᎱ,ەⰍ,ᐠᱻ,ܙเ,ހߴ,ㆵꜤ,ᡍⲲ,ㆵꜤ,ܪˑ,ꓸꧦ,ꓸꧦ,ꓸꧦ,ᒡꙿ,ᠸՙ,ʿˌ,ᒡˋ,ᔅ〵,ⵆޚ,ހߴ,ⵈᒾ,ހߴ,ﾟஃ,ㆵꜤ,ㆵʹ,ᐟถ,ᢏང,ᑉᐩ,ᣟʾ,ᠸՙ,ᢥᄼ,ހߴ,ⵈᒾ,ހߴ,ⵓถ,ᣞꓸ,ᣞꓸ,ᠢۂ,ᠫܕ,ᱹܘ,ᱹܘ,ᖕꙿ,ᠫᑊ,ᢏང,ᢏང,ޚว,ⵆޚ,ᠥߴ,ʹꓼ,ەⰍ,ⵓถ,ޚว,ᠥߴ,ⵆޚ,ʹꓼ,ᐠต,ᖕꙿ,ᐥː,ʹꓼ,ەⰍ,ᠥߴ,ᱹܘ,ᠥߴ,ᐠต,ᱼᱺ,اʹ,ᛍᄾ,ᡍⲲ,ꓸꧦ,ꓸꧦ,اۃ,ㆵʹ,ꜘ〳,ㆵꜤ,ʹꓼ,ⵓถ,ᣞꓸ,ᱺˉ,ᕝヾ,ⵓถ,ᣞꓸ,ᣞꓸ,ᠢۂ,ᢏང,ᠫܕ,ᱹܘ,ހߴ,ⵈᒾ,ހߴ,اۃ,اۃ,ꓸꧦ,ᢦᒻ,ㆵʹ,ܪˑ,ꜘ〳,ᱺˉ,ᛧޚ,ٴา,ᒡꙿ,ⴰߪ,ᐥː,ހߴ,ⵈᒾ,ހߴ,ᠢۂ,ᠫᑊ,ᣞꓸ,ހߴ,ⵈᒾ,ހߴ,ᒢᆞ,ᠢۂ,ⵆޚ,ᐥː,اʹ,ᐠᱻ,ހߴ,ⵈᒾ,ހߴ,ﾟஃ,ꓸꧦ,ꜘ〳,ܪˑ,ᡍⲲ,ꜘ〳,ᠶᎱ,ᠶา,ᢥᄼ,اʹ,ʾˬ,ᣟʾ,ᣟʾ,ހߴ,ⵈᒾ,ހߴ,ܪˑ,ꓸꧦ,ꜘ〳,اۃ,ㆵʹ,ᡍⲲ,ㆵʹ,ʿˌ,ᐥː,ٴา,ەⰍ,ᕝヾ,ᠢۂ,ހߴ,ⵈᒾ,ހߴ,ᠶᎱ,ᱺˉ,ᛧޚ,ᓒܢ,ᕝヾ,ޣˋ,ᐠต,ހߴ,ⵈᒾ,ހߴ,ﾟஃ,ﾟஃ,ᢦᒻ,ﾟஃ,ܪˑ,ᐥː,ᱼᱺ,ᢏݚ,ᑉᐩ,ˆᄾ,ᓒܢ,ހߴ,ⵈᒾ,ހߴ,ㆵʹ,ﾟஃ,ᢦᒻ,ㆵʹ,ﾟஃ,ꓸꧦ,اۃ,ᠫᑊ,ᠶา,އء,ᒡˋ,ᕝヾ,ᠫᑊ,ހߴ,ⵈᒾ,ހߴ,ᠶᎱ,ᢦᒻ,ꜘ〳,ᢦᒻ,ㆵꜤ,ᢦᒻ,ܪˑ,ᠲゝ,ˆᄾ,ܪߪ,ᔇˇ,ᔅ〵,ꞈร,ހߴ,ⵈᒾ,ހߴ,ⵓถ,ᣞꓸ,ᣞꓸ,ᠢۂ,ᠫܕ,ᱹܘ,ᱹܘ,ꜘ〳,ᡍⲲ,ᢏང,ⵓถ,ᠫᑊ,އء,ⵆޚ,ʹꓼ,ᛧꞋ,اʹ,ᢏང,ᠫᑊ,ޚว,ʹꓼ,ᱺˉ,اʹ,ᱹܘ,ᢏང,اʹ,ⵆޚ,ᖕꙿ,ەⰍ,ⵓถ,ᚒᒾ,ܙས,اʹ,ᛧꞋ,ᐠᱻ,ހߴ,ⵈᒾ,ހߴ,ⵆޚ,ˆᄾ,ⵆޚ,ⴰߪ,ހߴ,ʹۃ,ᢦˆ,ᛍᄾ,ꓸꧦ,ⴰߪ,ەⰍ,ꙿˏ,ﾟஃ,ꜘ〳,ᐠᱻ,ꙿˏ,ᠫᑊ,ᠥߴ,ەⰍ,ᣞꓸ,ޚว,ᐠต,ᠥߴ,ˈང,ᐝᱺ,ˈܙ,ᖕꙿ,اʹ,ᣞꓸ,ᠫᑊ,ᖕꙿ,ᠥߴ,ᕐہ,ᛍᄾ,ꓸꧦ,ⴰߪ,ㆵʹ,ܪˑ,اʹ,ꙿˏ,ᠶᎱ,ەⰍ,ᢦˆ,ᛍꓸ,ᢦˆ,ᖕꙿ,اʹ,ᣞꓸ,ᠫᑊ,ᖕꙿ,ᠥߴ,ᕐہ,ᛍᄾ,ꓸꧦ,ⴰߪ,ەⰍ,ꙿˏ,ﾟஃ,ꜘ〳,ˈང,ᐝᱺ,ᢦˆ,ᛍꓸ,ˈང,ꙿˏ,ᠫᑊ,ᠥߴ,ەⰍ,ᣞꓸ,ޚว,ᐠต,ᠥߴ,ˈང,ᛍᄾ,ꓸꧦ,ⴰߪ,ㆵʹ,ᢦᒻ,ᡍⲲ,اۃ,ㆵʹ,ᡍⲲ,ⵈᒾ,ᛍᄾ,ꓸꧦ,ⴰߪ,ㆵʹ,ᡍⲲ,اʹ,اۃ,ەⰍ,ᱼᱺ,ᐝᱺ,ˈܙ,ͺⲲ,ⵆޚ,ᖕꙿ,ᕐہ,ᛍᄾ,ꓸꧦ,ⴰߪ,ܪˑ,ᢦᒻ,އء,ەⰍ,ᠶᎱ,ᱼᱺ,ᐠᱻ,ᛍᄾ,ꓸꧦ,ⴰߪ,اۃ,اۃ,ەⰍ,އء,ⵈᒾ,ᛍᄾ,ꓸꧦ,ⴰߪ,ܪˑ,ⵆޚ,ꓸꧦ,ᢦᒻ,ꙿˏ,ᠶᎱ,ᐠᱻ,ᛍᄾ,ꓸꧦ,ⴰߪ,ㆵʹ,ᢦᒻ,ᡍⲲ,اۃ,ㆵʹ,ᡍⲲ,ˈང,ᐝᱺ,ᢦˆ,ᓒܢ,ⵓถ,ޚว,ᕝヾ,اʹ,ˈང,ʿˏ,ʿˏ,ܙเ,ʹۃ,ᐝᱺ,ˈܙ,ᣞꓸ,ᖕꙿ,ᛧꞋ,ˈܙ,ͺⲲ,ⵆޚ,ᖕꙿ,ᕐہ,ᛍᄾ,ꓸꧦ,ⴰߪ,اʹ,ەⰍ,ܪˑ,ﾟஃ,اۃ,ꓸꧦ,ᐠᱻ,ᓪه,ᠢۂ,ⵆޚ,ᖕꙿ,ᢏང,اʹ,ᑉᐩ,ᠥߴ,ᣞꓸ,ˈང,ᛍᄾ,ꓸꧦ,ⴰߪ,ܪˑ,ᢦᒻ,އء,ەⰍ,ᠶᎱ,ᱼᱺ,ˈང,ꓸꧦ,ⴰߪ,اʹ,ⵆޚ,ᐝᱺ,ᐝᱺ,ᱹܘ,ꓸꧦ,ⴰߪ,ﾟஃ,ᖦเ,ˈང,ᓪه,ᠢۂ,ⵆޚ,ᖕꙿ,ᢏང,اʹ,ᑉᐩ,ᠥߴ,ᣞꓸ,ˈང,ᛍᄾ,ꓸꧦ,ⴰߪ,ܪˑ,ᢦᒻ,އء,ەⰍ,ᠶᎱ,ᱼᱺ,ˈང,ꓸꧦ,ⴰߪ,ꙿˏ,ꓸꧦ,ᐝᱺ,ᐝᱺ,ᱹܘ,ꓸꧦ,ⴰߪ,ㆵʹ,ᐝᱺ,ޙᡃ,ᓪه,ᠢۂ,ⵆޚ,ᖕꙿ,ᢏང,اʹ,ᑉᐩ,ᠥߴ,ᣞꓸ,ˈང,ᛍᄾ,ꓸꧦ,ⴰߪ,ܪˑ,ᢦᒻ,އء,ەⰍ,ᠶᎱ,ᱼᱺ,ˈང,ꓸꧦ,ⴰߪ,اʹ,އء,ᐝᱺ,ᐝᱺ,ᱹܘ,ꓸꧦ,ⴰߪ,ܪˑ,ޙᡃ,ᠢۂ,ⵆޚ,ᖕꙿ,ᢏང,اʹ,ᑉᐩ,ᠥߴ,ᣞꓸ,ˈང,ᛍᄾ,ꓸꧦ,ⴰߪ,ܪˑ,ᢦᒻ,އء,ەⰍ,ᠶᎱ,ᱼᱺ,ˈང,ꓸꧦ,ⴰߪ,اʹ,ᢦᒻ,ᐝᱺ,ᐝᱺ,ᱹܘ,ꓸꧦ,ⴰߪ,اۃ,ᖦเ,ˈང,ᓪه,ᠢۂ,ⵆޚ,ᖕꙿ,ᢏང,اʹ,ᑉᐩ,ᠥߴ,ᣞꓸ,ˈང,ᛍᄾ,ꓸꧦ,ⴰߪ,ܪˑ,ᢦᒻ,އء,ەⰍ,ᠶᎱ,ᱼᱺ,ˈང,ꓸꧦ,ⴰߪ,اʹ,ᡍⲲ,ᐝᱺ,ᐝᱺ,ᱹܘ,ꓸꧦ,ⴰߪ,ᠶᎱ,ᐝᱺ,ޙᡃ,ᠢۂ,ⵆޚ,ᖕꙿ,ᢏང,اʹ,ᑉᐩ,ᠥߴ,ᣞꓸ,ˈང,ᛍᄾ,ꓸꧦ,ⴰߪ,ܪˑ,ᢦᒻ,އء,ەⰍ,ᠶᎱ,ᱼᱺ,ˈང,ꓸꧦ,ⴰߪ,ꙿˏ,ㆵʹ,ᐝᱺ,ᐝᱺ,ᱹܘ,ꓸꧦ,ⴰߪ,ꜘ〳,ޙᡃ,ᠢۂ,ⵆޚ,ᖕꙿ,ᢏང,اʹ,ᑉᐩ,ᠥߴ,ᣞꓸ,ˈང,ᛍᄾ,ꓸꧦ,ⴰߪ,ܪˑ,ᢦᒻ,އء,ەⰍ,ᠶᎱ,ᱼᱺ,ˈང,ꓸꧦ,ⴰߪ,اʹ,ㆵꜤ,ᐝᱺ,ᐝᱺ,ᱹܘ,ꓸꧦ,ⴰߪ,ㆵꜤ,ޙᡃ,ᠢۂ,ⵆޚ,ᖕꙿ,ᢏང,اʹ,ᑉᐩ,ᠥߴ,ᣞꓸ,ˈང,ᛍᄾ,ꓸꧦ,ⴰߪ,ܪˑ,ᢦᒻ,އء,ەⰍ,ᠶᎱ,ᱼᱺ,ˈང,ꓸꧦ,ⴰߪ,اʹ,ꙿˏ,ᐝᱺ,ᐝᱺ,ᱹܘ,ꓸꧦ,ⴰߪ,ᢦᒻ,ޙᡃ,ᓪه,ᠢۂ,ⵆޚ,ᖕꙿ,ᢏང,اʹ,ᑉᐩ,ᠥߴ,ᣞꓸ,ˈང,ᛍᄾ,ꓸꧦ,ⴰߪ,ܪˑ,ᢦᒻ,އء,ەⰍ,ᠶᎱ,ᱼᱺ,ˈང,ꓸꧦ,ⴰߪ,اʹ,ەⰍ,ᐝᱺ,ᐝᱺ,ᱹܘ,ꓸꧦ,ⴰߪ,ᡍⲲ,ᢦˆ,ޚว,ꙿˏ,ˈང,ᛍᄾ,ꓸꧦ,ⴰߪ,اʹ,ەⰍ,ܪˑ,ﾟஃ,اۃ,ꓸꧦ,ᐠᱻ,ᐠᱻ,ᐠᱻ,ᛍᄾ,ꓸꧦ,ⴰߪ,ㆵʹ,ᡍⲲ,اʹ,اۃ,ەⰍ,ᱼᱺ,ᐝᱺ,އء,ᖕꙿ,اʹ,ⵆޚ,ܙས,ᢦˆ,اʹ,ᕝヾ,ᢏང,اʹ,ᕐہ,ᛍᄾ,ꓸꧦ,ⴰߪ,ܪˑ,ⵆޚ,ꓸꧦ,ᢦᒻ,ꙿˏ,ᠶᎱ,ܙเ,ހߴ,ᠢۂ,ᠫᑊ,ᢏང,ⵓถ,ހߴ,ʹۃ,ˈང,ᛍᄾ,ꓸꧦ,ⴰߪ,ܪˑ,ⵆޚ,ꓸꧦ,ᢦᒻ,ꙿˏ,ᠶᎱ,ܙเ,ހߴ,ᢏང,ⵓถ,ޚว,ꙿˏ,ᣞꓸ,ހߴ,ʹۃ,ˈང,ᐝᱺ,ᐝᱺ,ᢦˆ,ᛍꓸ,ەⰍ,ⵆޚ,ᣞꓸ,ەⰍ,ⵓถ,ˈང,ᛍᄾ,ꓸꧦ,ⴰߪ,ᠶᎱ,اʹ,ㆵʹ,ꙿˏ,اۃ,ⵆޚ,ᐝᱺ,ˈܙ,ᛍᄾ,ꓸꧦ,ⴰߪ,ܪˑ,ⵆޚ,ꓸꧦ,ᢦᒻ,ꙿˏ,ᠶᎱ,ܙเ,ހߴ,ᠢۂ,ᠫᑊ,ᢏང,ⵓถ,ހߴ,ʹۃ,ˈང,ᛍᄾ,ꓸꧦ,ⴰߪ,ܪˑ,ⵆޚ,ꓸꧦ,ᢦᒻ,ꙿˏ,ᠶᎱ,ܙเ,ހߴ,ᢏང,ⵓถ,ޚว,ꙿˏ,ᣞꓸ,ހߴ,ʹۃ,ˈང,ᐝᱺ,ᐝᱺ,ᢦˆ,ᛍꓸ,ᛍꓸ,ᛍꓸ,ˈང,ᛍᄾ,ꓸꧦ,ⴰߪ,ەⰍ,ꙿˏ,ﾟஃ,ꜘ〳,ⵈᒾ,ꓸꧦ,ⴰߪ,އء,ᢦᒻ,ꓸꧦ,ܪˑ,اۃ,ᐝᱺ,ⵈᒾ,ᖕꙿ,اʹ,ᐠᱻ,ᛍᄾ,ꓸꧦ,ⴰߪ,ᠶᎱ,ᡍⲲ,ᢦᒻ,اʹ,ᡍⲲ,ꙿˏ,ˈང,ꓸꧦ,ⴰߪ,اʹ,ᱼᱺ,ᐝᱺ,ޙᡃ,ܙས,اʹ,ᛧꞋ,ޙᡃ,ᛍᄾ,ꓸꧦ,ⴰߪ,ᠶᎱ,ᡍⲲ,ᢦᒻ,اʹ,ᡍⲲ,ꙿˏ,ˈང,ꓸꧦ,ⴰߪ,اʹ,ꜘ〳,ᐝᱺ,ޙᡃ,ᠢۂ,ⵆޚ,ᐥː,اʹ,ⵈᒾ,ᠫᑊ,ᖕꙿ,ᐠᱻ,ˆᄾ,ⵆޚ,ͺⲲ,ⵆޚ,ܙเ,ᛍᄾ,ꓸꧦ,ⴰߪ,ᠶᎱ,ᡍⲲ,ᢦᒻ,اʹ,ᡍⲲ,ꙿˏ,ˈང,ꓸꧦ,ⴰߪ,اʹ,اʹ,ᐝᱺ,ʹۃ,ˈང,ᖕꙿ,اʹ,ᐝᱺ,ⵈᒾ,ˆᄾ,ⵆޚ,ͺⲲ,ⵆޚ,ܙเ,ᛍᄾ,ꓸꧦ,ⴰߪ,ᠶᎱ,ᡍⲲ,ᢦᒻ,اʹ,ᡍⲲ,ꙿˏ,ˈང,ꓸꧦ,ⴰߪ,اʹ,ᠶᎱ,ᐝᱺ,ʹۃ,ˈང,ހߴ,ᠫᑊ,ހߴ,ⵈᒾ,ᠫᑊ,ᖕꙿ,ᐝᱺ,ⵈᒾ,ᖕꙿ,ᐠᱻ,ᛍᄾ,ꓸꧦ,ⴰߪ,ᠶᎱ,ᡍⲲ,ᢦᒻ,اʹ,ᡍⲲ,ꙿˏ,ˈང,ꓸꧦ,ⴰߪ,ꙿˏ,ﾟஃ,ᐝᱺ,ᐝᱺ,ᢦˆ))})();r\n</js>",
    "weight": 0
  }
]